Workbook

Sheet Index
A1: NORTH COAL STATE OWNED CORPORATION
A2: ERP FORMS & STANDARD TEMPLATES - PLANNING AND POLICY MODULE
A3: Developer pack accompanying the approved System Architecture & BPR Report (20 September 2026) | Prepared by Crest Point Consulting Group | Version 1.0
A5: COLOUR LEGEND
A6: Yellow | B6: Field entered by a user (blue text = example data shown for illustration)
A7: Grey | B7: Auto-populated / auto-calculated by the system
A8: Light grey | B8: Not applicable on this form
A9: Navy | B9: Section / column headers and signature-block titles
A11: Form Code | B11: Sheet (click to open) | C11: Purpose | D11: Source in approved report
A12: PL-01 | B12: PL-01 Plan Item Creation | C12: Dynamic plan item: class, category, CoA link or N/A | D12: 4.7.2 Dynamic Plan Item Creation
A13: PL-02 | B13: PL-02 Plan Approval Record | C13: Plan submission, completeness review and Head approval | D13: 4.7.5 Workflow 1
A14: PL-03 | B14: PL-03 Operational Plan | C14: Monthly excavation and extraction targets per Second Unit | D14: 4.7.2 Operational Plan
A15: PL-04 | B15: PL-04 Financial Plan | C15: Monthly revenue, cost and CAPEX plan with auto planned P&L | D15: 4.7.2 Comprehensive Financial, P&L and CAPEX Plan
A16: PL-05 | B16: PL-05 Actual Volume Entry | C16: Manual actual volumes with mandatory reference document | D16: 4.7.2 Non-Financial Metric Exemption; 4.7.4
A17: PL-06 | B17: PL-06 Variance Analysis | C17: Plan vs actual variance (absolute and %) with alert status | D17: 4.7.2 Variance Analysis
A18: PL-07 | B18: PL-07 Alert Parameters & Log | C18: Variance thresholds and the alert log | D18: 4.7.2 Automated Variance Alerts
A19: PL-08 | B19: PL-08 Actual vs Planned P&L | C19: Real-time Actual vs Planned P&L report layout | D19: 4.7.2 Automated Planned vs Actual P&L
A20: PL-09 | B20: PL-09 Plan Amendment Request | C20: Amendment with mandatory ED approval reference | D20: 4.7.2 Plan Amendment Protocol; Workflow 3
A21: PL-10 | B21: PL-10 Correspondence Register | C21: Digital in/out correspondence register (addition) | D21: 4.7.1 As-Is activity / pain point
A22: PL-11 | B22: PL-11 Correction Request | C22: Standard officer correction request (Planning) | D22: 4.7.2 Officer Correction Request Workflow
... A25: PL-14 | B25: PL-14 Reports Spec | C25: Required planning reports and filters | D25: 4.7.4 Required Reports
A27: DESIGN RULES THAT APPLY TO EVERY FORM
A28: 1. Single currency: Afghan Afghani (AFN) for financial items; physical items use tonnes and cubic metres.
A29: 2. Planning posts NO accounting entries. Financial actuals are pulled live from Finance, Inventory, Sales and Procurement through Chart of Accounts links; physical actuals are entered manually against a mandatory reference document.
A30: 3. The Executive Director and Directors have no system access; annual plans and amendments are approved physically outside the ERP and only the reference is recorded. No ED / Director signature block appears on any printed form.
A31: 4. The approved Planning roles list no Internal Control step, so these forms have no "Verified by" block; IC keeps read-only access and sees every action in the Control Log.
A32: 5. Officers can never edit or delete a submitted entry; corrections follow PL-11. Every action is written to the Control Log (layout FA-18 in the Finance workbook), which no user can alter.
A33: 6. Plans are strictly isolated per Class (HQ or Second Unit); the Chart of Accounts has dedicated sub-accounts for each.
A34: 7. Names, items, volumes, amounts, thresholds and account codes are illustrative examples only.

Sheet PL-01 Plan Item Creation
A1: [Corporation logo] | C1: NORTH COAL STATE OWNED CORPORATION
C2: DYNAMIC PLAN ITEM CREATION
C3: Form PL-01 | Version 1.0 | Created by the Planning Officer; the item becomes part of the plan the Head approves
A5: A. ITEM DEFINITION (all five parameters are mandatory)
A6: Plan Item Ref. (auto) | C6: PLI-000045 | D6: Date Created | E6: 46283
A7: Item Name / Description | C7: Wood for excavation holes | D7: Class Assignment (Location) | E7: Second Unit A
A8: Financial Classification | C8: Direct Cost | D8: Unit of Measure | E8: AFN
A9: Chart of Accounts Linkage | C9: 5300-A Mining Consumables Expense - Second Unit A (example) | D9: Linkage Type (auto) | E9: =IF(C9="N/A","Non-financial - actuals entered manually with a reference document","Financial - actuals pulled automatically from the linked sub-account") -> Financial - actuals pulled automatically from the linked sub-account
A10: Item Status | C10: Draft | D10: Created By | E10: PLN-OFF-01
A11: Rule Check (system) | C11: =IF(AND(E8="AFN",C9="N/A"),"ERROR: a financial item must be linked to a Chart of Accounts sub-account",IF(AND(E8<>"AFN",C9<>"N/A"),"ERROR: a physical metric (tonnes / cubic metres) must be set to N/A",IF(OR(C7="",E7="",C8="",C9=""),"ERROR: all five parameters are mandatory","OK"))) -> OK
A13: B. EXAMPLES OF PLAN ITEMS
A14: No. | B14: Class | C14: Plan Item | D14: Financial Classification | E14: CoA Linkage | F14: Unit
A15: 1 | B15: Second Unit A | C15: Coal extraction (raw coal) | D15: N/A - Operational metric | E15: N/A | F15: Tonnes
A16: 2 | B16: Second Unit A | C16: Overburden excavation | D16: N/A - Operational metric | E16: N/A | F16: Cubic metres
A17: 3 | B17: Second Unit A | C17: Coal Sales Revenue | D17: Main Core Revenue | E17: 4100-A Coal Sales Revenue | F17: AFN
A18: 4 | B18: HQ | C18: Rental Income - Market Block A | D18: Non-Core Revenue | E18: 4200 Rental Income | F18: AFN
A19: 5 | B19: HQ | C19: Office supplies | D19: Indirect Cost | E19: 6500 Office Supplies Expense | F19: AFN
A20: 6 | B20: Second Unit A | C20: New mining truck | D20: CAPEX | E20: 1535 Motor Vehicles - Second Unit A | F20: AFN
A22: PREPARED BY (Planning Officer)
A23: Name:
A24: Position:
A25: Signature:
A26: Date:
A28: NOTES FOR DEVELOPERS
A29: 1. Every plan item carries a Class (HQ or a specific Second Unit) so budgets and targets are strictly isolated per location, a Financial Classification and a Chart of Accounts link for automated variance tracking.
A30: 2. The CoA includes dedicated sub-accounts for each Second Unit and HQ; a financial plan item is linked to its Second Unit's sub-account. Physical metrics (tonnes extracted, cubic metres excavated) are linked to "N/A" and their actuals are entered manually against a reference document.
A31: 3. The report lists five financial categories but does not say which category a physical metric takes; "N/A - Operational metric" is shown as a proposed option. Account codes shown are illustrative.
A32: 4. Name, position and date may be pre-filled by the system from the Control Log; signatures are by hand so the printed form can be archived in the hard file.

Sheet PL-02 Plan Approval Record
A1: [Corporation logo] | C1: NORTH COAL STATE OWNED CORPORATION
C2: ANNUAL PLAN SUBMISSION AND APPROVAL RECORD
C3: Form PL-02 | Version 1.0 | Plan becomes Active only after the Planning Department Head approves it in the system
A5: A. PLAN DETAILS
A6: Plan Ref. (auto) | C6: PLN-2026-OP-01 | D6: Fiscal Year | E6: FY-2026
A7: Plan Type | C7: Operational (Excavation and Extraction) | D7: Classes Covered | E7: Second Unit A, Second Unit B, Second Unit C
A8: Submitted By (Officer) | C8: PLN-OFF-01 | D8: Date Submitted | E8: 46290
A10: B. DEPARTMENT HEAD COMPLETENESS REVIEW
A11: No. | B11: Check | E11: Result | F11: Comment
A12: 1 | B12: All Classes (HQ and every Second Unit) covered | E12: Yes
A13: 2 | B13: Monthly and annual targets entered for every plan item | E13: Yes
A14: 3 | B14: Class, financial category and CoA link (or N/A) set on every item | E14: Yes
A15: 4 | B15: Annual totals reviewed for reasonableness | E15: Yes
A17: C. APPROVAL
A18: ED Physical Approval Ref. (hard copy - see note 2) | C18: ED-PLAN-2026-0007 | D18: Date of ED Physical Approval | E18: 46293
A19: Planning Dept Head Decision | C19: Approved | D19: Decision Date | E19: 46294
A20: Plan Status (system rule) | C20: =IF(AND(C19="Approved",COUNTIF(E12:E15,"No")=0,C18<>""),"ACTIVE - tracking begins; plan cannot be edited except through the Plan Amendment protocol",IF(C19="Approved","BLOCKED - completeness checks or ED approval reference missing","Not active - returned to the Planning Officer")) -> ACTIVE - tracking begins; plan cannot be edited except through the Plan Amendment protocol
A22: PREPARED BY (Planning Officer) | D22: APPROVED BY (Planning Department Head)
A23: Name: | D23: Name:
A24: Position: | D24: Position:
A25: Signature: | D25: Signature:
A26: Date: | D26: Date:
A28: NOTES FOR DEVELOPERS
A29: 1. Workflow: Officer creates items, assigns Class / category / CoA link, enters monthly and annual targets and submits -> Head reviews for completeness -> Head approves -> plan is Active and tracking begins.
A30: 2. ADDITION TO CONFIRM: the roles section says the ED approves all annual plans physically and the Head approves "verifying they match physical ED approvals", but the Workflow-1 steps and the record carry no ED approval reference (only amendments do). The reference field above is added so the Head can verify it.
A31: 3. Plans are entered for all Second Units and HQ and cannot be changed by Officers once submitted; the Officer cannot approve their own plan.
A32: 4. The Executive Director and Directors have no system access. Their physical approval of annual plans and amendments is obtained outside the ERP; the ERP records only the reference. No ED / Director signature block appears on these forms, and the Planning roles list no Internal Control step, so there are no "Verified by" blocks.

Sheet PL-03 Operational Plan
A1: [Corporation logo] | C1: NORTH COAL STATE OWNED CORPORATION
C2: ANNUAL OPERATIONAL PLAN - EXCAVATION AND EXTRACTION
C3: Form PL-03 | Version 1.0 | Physical targets by month and Second Unit | CoA linkage: N/A
A5: Plan Ref. / Fiscal Year | C5: PLN-2026-OP-01 / FY-2026 | G5: Plan Status | K5: Active
A7: Class | B7: Metric | C7: Unit | D7: CoA | E7: Jan | F7: Feb | G7: Mar | H7: Apr | I7: May | J7: Jun | K7: Jul | L7: Aug | M7: Sep | N7: Oct | O7: Nov | P7: Dec | Q7: Annual Total
A8: Second Unit A | B8: Excavation (overburden removal) | C8: m3 | D8: N/A | E8: 20000 | F8: 20000 | G8: 20000 | H8: 20000 | I8: 20000 | J8: 20000 | K8: 20000 | L8: 20000 | M8: 20000 | N8: 20000 | O8: 20000 | P8: 20000 | Q8: =IF(A8="","",SUM(E8:P8)) -> 240000
A9: Second Unit A | B9: Extraction (raw coal) | C9: Tonnes | D9: N/A | E9: 4000 | F9: 4000 | G9: 4500 | H9: 5000 | I9: 5500 | J9: 5500 | K9: 5500 | L9: 5500 | M9: 5500 | N9: 5500 | O9: 5000 | P9: 4500 | Q9: =IF(A9="","",SUM(E9:P9)) -> 60000
A10: Second Unit B | B10: Excavation (overburden removal) | C10: m3 | D10: N/A | E10: 9000 | F10: 9000 | G10: 9000 | H10: 9000 | I10: 9000 | J10: 9000 | K10: 9000 | L10: 9000 | M10: 9000 | N10: 9000 | O10: 9000 | P10: 9000 | Q10: =IF(A10="","",SUM(E10:P10)) -> 108000
A11: Second Unit B | B11: Extraction (raw coal) | C11: Tonnes | D11: N/A | E11: 2500 | F11: 2500 | G11: 2500 | H11: 2500 | I11: 2500 | J11: 2500 | K11: 2500 | L11: 2500 | M11: 2500 | N11: 2500 | O11: 2500 | P11: 2500 | Q11: =IF(A11="","",SUM(E11:P11)) -> 30000
A12: Second Unit C | B12: Excavation (overburden removal) | C12: m3 | D12: N/A | E12: 4000 | F12: 4000 | G12: 4000 | H12: 4000 | I12: 4000 | J12: 4000 | K12: 4000 | L12: 4000 | M12: 4000 | N12: 4000 | O12: 4000 | P12: 4000 | Q12: =IF(A12="","",SUM(E12:P12)) -> 48000
A13: Second Unit C | B13: Extraction (raw coal) | C13: Tonnes | D13: N/A | E13: 1200 | F13: 1200 | G13: 1200 | H13: 1200 | I13: 1200 | J13: 1200 | K13: 1200 | L13: 1200 | M13: 1200 | N13: 1200 | O13: 1200 | P13: 1200 | Q13: =IF(A13="","",SUM(E13:P13)) -> 14400
Q14: =IF(A14="","",SUM(E14:P14))
Q15: =IF(A15="","",SUM(E15:P15))
Q16: =IF(A16="","",SUM(E16:P16))
Q17: =IF(A17="","",SUM(E17:P17))
A19: TOTALS BY METRIC (all Classes) | E19: Jan | F19: Feb | G19: Mar | H19: Apr | I19: May | J19: Jun | K19: Jul | L19: Aug | M19: Sep | N19: Oct | O19: Nov | P19: Dec | Q19: Annual
A20: Excavation (m3) | E20: =SUMIF($B$8:$B$17,"Excavation (overburden removal)",E$8:E$17) -> 33000 | F20: =SUMIF($B$8:$B$17,"Excavation (overburden removal)",F$8:F$17) -> 33000 | G20: =SUMIF($B$8:$B$17,"Excavation (overburden removal)",G$8:G$17) -> 33000 | H20: =SUMIF($B$8:$B$17,"Excavation (overburden removal)",H$8:H$17) -> 33000 | I20: =SUMIF($B$8:$B$17,"Excavation (overburden removal)",I$8:I$17) -> 33000 | J20: =SUMIF($B$8:$B$17,"Excavation (overburden removal)",J$8:J$17) -> 33000 | K20: =SUMIF($B$8:$B$17,"Excavation (overburden removal)",K$8:K$17) -> 33000 | L20: =SUMIF($B$8:$B$17,"Excavation (overburden removal)",L$8:L$17) -> 33000 | ... Q20: =SUMIF($B$8:$B$17,"Excavation (overburden removal)",Q$8:Q$17) -> 396000
A21: Extraction (tonnes) | E21: =SUMIF($B$8:$B$17,"Extraction (raw coal)",E$8:E$17) -> 7700 | F21: =SUMIF($B$8:$B$17,"Extraction (raw coal)",F$8:F$17) -> 7700 | G21: =SUMIF($B$8:$B$17,"Extraction (raw coal)",G$8:G$17) -> 8200 | H21: =SUMIF($B$8:$B$17,"Extraction (raw coal)",H$8:H$17) -> 8700 | I21: =SUMIF($B$8:$B$17,"Extraction (raw coal)",I$8:I$17) -> 9200 | J21: =SUMIF($B$8:$B$17,"Extraction (raw coal)",J$8:J$17) -> 9200 | K21: =SUMIF($B$8:$B$17,"Extraction (raw coal)",K$8:K$17) -> 9200 | L21: =SUMIF($B$8:$B$17,"Extraction (raw coal)",L$8:L$17) -> 9200 | ... Q21: =SUMIF($B$8:$B$17,"Extraction (raw coal)",Q$8:Q$17) -> 104400
A23: NOTES FOR DEVELOPERS
A24: 1. Operational plan = planned volume of overburden removal (cubic metres) and raw coal extraction (tonnes) by month and Second Unit; entered at the start of each fiscal year. CoA linkage is N/A, so actuals are entered manually against reference documents (PL-05).
A25: 2. Approved by the Planning Department Head (PL-02). Seasonal values and quantities shown are illustrative.
A26: 3. Name, position and date may be pre-filled by the system from the Control Log; signatures are by hand so the printed form can be archived in the hard file.
A27: PREPARED BY (Planning Officer) | I27: APPROVED BY (Planning Department Head)
A28: Name: | I28: Name:
A29: Position: | I29: Position:
A30: Signature: | I30: Signature:
A31: Date: | I31: Date:

Sheet PL-04 Financial Plan
A1: [Corporation logo] | C1: NORTH COAL STATE OWNED CORPORATION
C2: ANNUAL FINANCIAL PLAN - P&L AND CAPEX
C3: Form PL-04 | Version 1.0 | Month-by-month targets by Class, category and CoA sub-account (AFN)
A5: Plan Ref. / Fiscal Year | C5: PLN-2026-FIN-01 / FY-2026 | G5: Plan Status | K5: Active
A7: Class | B7: Plan Item | C7: Category | D7: CoA Linkage | E7: Jan | F7: Feb | G7: Mar | H7: Apr | I7: May | J7: Jun | K7: Jul | L7: Aug | M7: Sep | N7: Oct | O7: Nov | P7: Dec | Q7: Annual Total
A8: Second Unit A | B8: Coal Sales Revenue | C8: Main Core Revenue | D8: 4100-A Coal Sales Revenue - Second Unit A | E8: 2500000 | F8: 2500000 | G8: 2500000 | H8: 2500000 | I8: 2500000 | J8: 2500000 | K8: 2500000 | L8: 2500000 | M8: 2500000 | N8: 2500000 | O8: 2500000 | P8: 2500000 | Q8: =IF(A8="","",SUM(E8:P8)) -> 30000000
A9: Second Unit B | B9: Coal Sales Revenue | C9: Main Core Revenue | D9: 4100-B Coal Sales Revenue - Second Unit B | E9: 1800000 | F9: 1800000 | G9: 1800000 | H9: 1800000 | I9: 1800000 | J9: 1800000 | K9: 1800000 | L9: 1800000 | M9: 1800000 | N9: 1800000 | O9: 1800000 | P9: 1800000 | Q9: =IF(A9="","",SUM(E9:P9)) -> 21600000
A10: HQ | B10: Rental Income - Market Block A | C10: Non-Core Revenue | D10: 4200 Rental Income | E10: 100000 | F10: 100000 | G10: 100000 | H10: 100000 | I10: 100000 | J10: 100000 | K10: 100000 | L10: 100000 | M10: 100000 | N10: 100000 | O10: 100000 | P10: 100000 | Q10: =IF(A10="","",SUM(E10:P10)) -> 1200000
A11: Second Unit A | B11: Wood for excavation holes | C11: Direct Cost | D11: 5300-A Mining Consumables Expense - Second Unit A | E11: 300000 | F11: 300000 | G11: 300000 | H11: 300000 | I11: 300000 | J11: 300000 | K11: 300000 | L11: 300000 | M11: 300000 | N11: 300000 | O11: 300000 | P11: 300000 | Q11: =IF(A11="","",SUM(E11:P11)) -> 3600000
A12: Second Unit A | B12: Site workers wages | C12: Direct Cost | D12: 5200-A Wages Expense - Second Unit A | E12: 185000 | F12: 185000 | G12: 185000 | H12: 185000 | I12: 185000 | J12: 185000 | K12: 185000 | L12: 185000 | M12: 185000 | N12: 185000 | O12: 185000 | P12: 185000 | Q12: =IF(A12="","",SUM(E12:P12)) -> 2220000
A13: Second Unit B | B13: Site workers wages | C13: Direct Cost | D13: 5200-B Wages Expense - Second Unit B | E13: 240500 | F13: 240500 | G13: 240500 | H13: 240500 | I13: 240500 | J13: 240500 | K13: 240500 | L13: 240500 | M13: 240500 | N13: 240500 | O13: 240500 | P13: 240500 | Q13: =IF(A13="","",SUM(E13:P13)) -> 2886000
A14: HQ | B14: Administration salaries | C14: Indirect Cost | D14: 6100 Salary Expense - Administration | E14: 520000 | F14: 520000 | G14: 520000 | H14: 520000 | I14: 520000 | J14: 520000 | K14: 520000 | L14: 520000 | M14: 520000 | N14: 520000 | O14: 520000 | P14: 520000 | Q14: =IF(A14="","",SUM(E14:P14)) -> 6240000
A15: HQ | B15: Office supplies | C15: Indirect Cost | D15: 6500 Office Supplies Expense | E15: 35000 | F15: 35000 | G15: 35000 | H15: 35000 | I15: 35000 | J15: 35000 | K15: 35000 | L15: 35000 | M15: 35000 | N15: 35000 | O15: 35000 | P15: 35000 | Q15: =IF(A15="","",SUM(E15:P15)) -> 420000
A16: Second Unit A | B16: New mining truck | C16: CAPEX | D16: 1535 Motor Vehicles - Second Unit A | E16: 0 | F16: 0 | G16: 6000000 | H16: 0 | I16: 0 | J16: 0 | K16: 0 | L16: 0 | M16: 0 | N16: 0 | O16: 0 | P16: 0 | Q16: =IF(A16="","",SUM(E16:P16)) -> 6000000
Q17: =IF(A17="","",SUM(E17:P17))
Q18: =IF(A18="","",SUM(E18:P18))
Q19: =IF(A19="","",SUM(E19:P19))
A21: PLANNED PROFIT OR LOSS (auto-generated) | Q21: Annual (AFN)
A22: Planned Revenue (Core + Non-Core) | Q22: =SUMIF($C$8:$C$19,"Main Core Revenue",Q$8:Q$19)+SUMIF($C$8:$C$19,"Non-Core Revenue",Q$8:Q$19) -> 52800000
A23: Less: Direct Costs | Q23: =SUMIF($C$8:$C$19,"Direct Cost",Q$8:Q$19) -> 8706000
A24: Gross Profit | Q24: =Q22-Q23 -> 44094000
A25: Less: Indirect Costs | Q25: =SUMIF($C$8:$C$19,"Indirect Cost",Q$8:Q$19) -> 6660000
A26: PLANNED PROFIT / (LOSS) | Q26: =Q24-Q25 -> 37434000
A27: Memo: Planned CAPEX (not in P&L) | Q27: =SUMIF($C$8:$C$19,"CAPEX",Q$8:Q$19) -> 6000000
A29: PREPARED BY (Planning Officer) | I29: APPROVED BY (Planning Department Head)
A30: Name: | I30: Name:
A31: Position: | I31: Position:
A32: Signature: | I32: Signature:
A33: Date: | I33: Date:
A35: NOTES FOR DEVELOPERS
A36: 1. Planned P&L is generated automatically from the plan: Revenue (Core + Non-Core) - Direct Costs = Gross Profit; - Indirect Costs = Profit or Loss. CAPEX is a budget for fixed-asset purchases and sits outside the P&L.
A37: 2. Rental income and wages figures echo the examples in the Properties and Payroll workbooks. All amounts and account codes are illustrative; CoA sub-accounts per Second Unit are created by Finance (FA-14).

Sheet PL-05 Actual Volume Entry
A1: [Corporation logo] | C1: NORTH COAL STATE OWNED CORPORATION
C2: ACTUAL OPERATIONAL VOLUME ENTRY (NON-FINANCIAL METRICS)
C3: Manual entry by the Planning Officer, backed by verified physical documents - does not touch the general ledger
A5: Entered By (Officer) | C5: PLN-OFF-01 | D5: Entry Period | G5: October 2026
A7: No. | B7: Class | C7: Metric | D7: Period | E7: Planned Volume (auto) | F7: Actual Volume Entered | G7: Unit | H7: Reference Document No. (mandatory) | I7: Document Type | J7: Validation (auto)
A8: 1 | B8: Second Unit A | C8: Extraction (raw coal) | D8: Oct-2026 | E8: 5500 | F8: 4700 | G8: Tonnes | H8: SER-A-2026-10-01 | I8: Signed site extraction report | J8: =IF(B8="","",IF(OR(H8="",I8=""),"BLOCKED - reference document number and type are mandatory",IF(F8>3*E8,"WARNING - actual is over 3x the plan; check for a typing error (e.g. 4,000 keyed as 40,000)","OK"))) -> OK
A9: 2 | B9: Second Unit A | C9: Excavation (overburden removal) | D9: Oct-2026 | E9: 20000 | F9: 19200 | G9: m3 | H9: SER-A-2026-10-02 | I9: Signed site excavation report | J9: =IF(B9="","",IF(OR(H9="",I9=""),"BLOCKED - reference document number and type are mandatory",IF(F9>3*E9,"WARNING - actual is over 3x the plan; check for a typing error (e.g. 4,000 keyed as 40,000)","OK"))) -> OK
A10: 3 | B10: Second Unit B | C10: Extraction (raw coal) | D10: Oct-2026 | E10: 2500 | F10: 2450 | G10: Tonnes | H10: SER-B-2026-10-01 | I10: Signed site extraction report | J10: =IF(B10="","",IF(OR(H10="",I10=""),"BLOCKED - reference document number and type are mandatory",IF(F10>3*E10,"WARNING - actual is over 3x the plan; check for a typing error (e.g. 4,000 keyed as 40,000)","OK"))) -> OK
A11: 4 | B11: Second Unit C | C11: Extraction (raw coal) | D11: Oct-2026 | E11: 1200 | F11: 1190 | G11: Tonnes | J11: =IF(B11="","",IF(OR(H11="",I11=""),"BLOCKED - reference document number and type are mandatory",IF(F11>3*E11,"WARNING - actual is over 3x the plan; check for a typing error (e.g. 4,000 keyed as 40,000)","OK"))) -> BLOCKED - reference document number and type are mandatory
A12: 5 | B12: Second Unit C | C12: Excavation (overburden removal) | D12: Oct-2026 | E12: 4000 | F12: 40000 | G12: m3 | H12: SER-C-2026-10-02 | I12: Signed site excavation report | J12: =IF(B12="","",IF(OR(H12="",I12=""),"BLOCKED - reference document number and type are mandatory",IF(F12>3*E12,"WARNING - actual is over 3x the plan; check for a typing error (e.g. 4,000 keyed as 40,000)","OK"))) -> WARNING - actual is over 3x the plan; check for a typing error (e.g. 4,000 keyed as 40,000)
A13: 6 | J13: =IF(B13="","",IF(OR(H13="",I13=""),"BLOCKED - reference document number and type are mandatory",IF(F13>3*E13,"WARNING - actual is over 3x the plan; check for a typing error (e.g. 4,000 keyed as 40,000)","OK")))
A14: 7 | J14: =IF(B14="","",IF(OR(H14="",I14=""),"BLOCKED - reference document number and type are mandatory",IF(F14>3*E14,"WARNING - actual is over 3x the plan; check for a typing error (e.g. 4,000 keyed as 40,000)","OK")))
A15: 8 | J15: =IF(B15="","",IF(OR(H15="",I15=""),"BLOCKED - reference document number and type are mandatory",IF(F15>3*E15,"WARNING - actual is over 3x the plan; check for a typing error (e.g. 4,000 keyed as 40,000)","OK")))
A16: 9 | J16: =IF(B16="","",IF(OR(H16="",I16=""),"BLOCKED - reference document number and type are mandatory",IF(F16>3*E16,"WARNING - actual is over 3x the plan; check for a typing error (e.g. 4,000 keyed as 40,000)","OK")))
A17: 10 | J17: =IF(B17="","",IF(OR(H17="",I17=""),"BLOCKED - reference document number and type are mandatory",IF(F17>3*E17,"WARNING - actual is over 3x the plan; check for a typing error (e.g. 4,000 keyed as 40,000)","OK")))
A19: NOTES FOR DEVELOPERS
A20: 1. Every manual actual must carry a Reference Document number (e.g. a signed site extraction report); the system rejects an entry without it. Entries do not affect the financial general ledger.
A21: 2. Entry No. 4 (Second Unit C extraction) shows the missing-reference block; entry No. 5 shows a suggested plausibility check for the typing error the report mentions (5,000 tonnes keyed as 50,000). The plausibility check is a suggestion, not an approved feature.
A22: 3. An Officer cannot edit or delete a submitted actual; corrections follow the request workflow in PL-11.
A24: ENTERED BY (Planning Officer)
A25: Name:
A26: Position:
A27: Signature:
A28: Date:

Sheet PL-06 Variance Analysis
A1: [Corporation logo] | C1: NORTH COAL STATE OWNED CORPORATION
C2: PLAN VS ACTUAL VARIANCE ANALYSIS
C3: Real-time report - financial and operational lines in one engine | Period: October 2026 (example)
A5: Class | B5: Plan Line | C5: Type | D5: Unit | E5: Planned | F5: Actual | G5: Variance (absolute) | H5: Variance % | I5: Direction | J5: Alert Threshold % | K5: Status (auto)
A6: Second Unit A | B6: Coal extraction | C6: Operational | D6: Tonnes | E6: 5500 | F6: 4700 | G6: =IF(A6="","",F6-E6) -> -800 | H6: =IF(A6="","",IF(N(E6)=0,"n/a",G6/E6)) -> -0.14545455 | I6: Higher is better | J6: 0.1 | K6: =IF(A6="","",IF(H6="n/a","n/a - no plan",IF(I6="Higher is better",IF(H6<-J6,"ALERT - below plan beyond threshold",IF(H6<0,"Below plan - within threshold","On or above plan")),IF(H6>J6,"ALERT - above plan beyond threshold",IF(H6>0,"Above plan - within threshold","On or below plan"))))) -> ALERT - below plan beyond threshold
A7: Second Unit A | B7: Overburden excavation | C7: Operational | D7: m3 | E7: 20000 | F7: 19200 | G7: =IF(A7="","",F7-E7) -> -800 | H7: =IF(A7="","",IF(N(E7)=0,"n/a",G7/E7)) -> -0.04 | I7: Higher is better | J7: 0.1 | K7: =IF(A7="","",IF(H7="n/a","n/a - no plan",IF(I7="Higher is better",IF(H7<-J7,"ALERT - below plan beyond threshold",IF(H7<0,"Below plan - within threshold","On or above plan")),IF(H7>J7,"ALERT - above plan beyond threshold",IF(H7>0,"Above plan - within threshold","On or below plan"))))) -> Below plan - within threshold
A8: Second Unit B | B8: Coal extraction | C8: Operational | D8: Tonnes | E8: 2500 | F8: 2450 | G8: =IF(A8="","",F8-E8) -> -50 | H8: =IF(A8="","",IF(N(E8)=0,"n/a",G8/E8)) -> -0.02 | I8: Higher is better | J8: 0.1 | K8: =IF(A8="","",IF(H8="n/a","n/a - no plan",IF(I8="Higher is better",IF(H8<-J8,"ALERT - below plan beyond threshold",IF(H8<0,"Below plan - within threshold","On or above plan")),IF(H8>J8,"ALERT - above plan beyond threshold",IF(H8>0,"Above plan - within threshold","On or below plan"))))) -> Below plan - within threshold
A9: Second Unit A | B9: Coal Sales Revenue | C9: Financial | D9: AFN | E9: 2500000 | F9: 2150000 | G9: =IF(A9="","",F9-E9) -> -350000 | H9: =IF(A9="","",IF(N(E9)=0,"n/a",G9/E9)) -> -0.14 | I9: Higher is better | J9: 0.1 | K9: =IF(A9="","",IF(H9="n/a","n/a - no plan",IF(I9="Higher is better",IF(H9<-J9,"ALERT - below plan beyond threshold",IF(H9<0,"Below plan - within threshold","On or above plan")),IF(H9>J9,"ALERT - above plan beyond threshold",IF(H9>0,"Above plan - within threshold","On or below plan"))))) -> ALERT - below plan beyond threshold
A10: Second Unit A | B10: Wood for excavation holes (direct cost) | C10: Financial | D10: AFN | E10: 300000 | F10: 372000 | G10: =IF(A10="","",F10-E10) -> 72000 | H10: =IF(A10="","",IF(N(E10)=0,"n/a",G10/E10)) -> 0.24 | I10: Lower is better | J10: 0.15 | K10: =IF(A10="","",IF(H10="n/a","n/a - no plan",IF(I10="Higher is better",IF(H10<-J10,"ALERT - below plan beyond threshold",IF(H10<0,"Below plan - within threshold","On or above plan")),IF(H10>J10,"ALERT - above plan beyond threshold",IF(H10>0,"Above plan - within threshold","On or below plan"))))) -> ALERT - above plan beyond threshold
A11: Second Unit B | B11: Site workers wages (direct cost) | C11: Financial | D11: AFN | E11: 240500 | F11: 246000 | G11: =IF(A11="","",F11-E11) -> 5500 | H11: =IF(A11="","",IF(N(E11)=0,"n/a",G11/E11)) -> 0.022869023 | I11: Lower is better | J11: 0.15 | K11: =IF(A11="","",IF(H11="n/a","n/a - no plan",IF(I11="Higher is better",IF(H11<-J11,"ALERT - below plan beyond threshold",IF(H11<0,"Below plan - within threshold","On or above plan")),IF(H11>J11,"ALERT - above plan beyond threshold",IF(H11>0,"Above plan - within threshold","On or below plan"))))) -> Above plan - within threshold
A12: HQ | B12: Office supplies (indirect cost) | C12: Financial | D12: AFN | E12: 35000 | F12: 33000 | G12: =IF(A12="","",F12-E12) -> -2000 | H12: =IF(A12="","",IF(N(E12)=0,"n/a",G12/E12)) -> -0.057142857 | I12: Lower is better | J12: 0.15 | K12: =IF(A12="","",IF(H12="n/a","n/a - no plan",IF(I12="Higher is better",IF(H12<-J12,"ALERT - below plan beyond threshold",IF(H12<0,"Below plan - within threshold","On or above plan")),IF(H12>J12,"ALERT - above plan beyond threshold",IF(H12>0,"Above plan - within threshold","On or below plan"))))) -> On or below plan
A13: HQ | B13: Rental Income - Market Block A | C13: Financial | D13: AFN | E13: 100000 | F13: 100000 | G13: =IF(A13="","",F13-E13) -> 0 | H13: =IF(A13="","",IF(N(E13)=0,"n/a",G13/E13)) -> 0 | I13: Higher is better | J13: 0.1 | K13: =IF(A13="","",IF(H13="n/a","n/a - no plan",IF(I13="Higher is better",IF(H13<-J13,"ALERT - below plan beyond threshold",IF(H13<0,"Below plan - within threshold","On or above plan")),IF(H13>J13,"ALERT - above plan beyond threshold",IF(H13>0,"Above plan - within threshold","On or below plan"))))) -> On or above plan
G14: =IF(A14="","",F14-E14) | H14: =IF(A14="","",IF(N(E14)=0,"n/a",G14/E14)) | K14: =IF(A14="","",IF(H14="n/a","n/a - no plan",IF(I14="Higher is better",IF(H14<-J14,"ALERT - below plan beyond threshold",IF(H14<0,"Below plan - within threshold","On or above plan")),IF(H14>J14,"ALERT - above plan beyond threshold",IF(H14>0,"Above plan - within threshold","On or below plan")))))
G15: =IF(A15="","",F15-E15) | H15: =IF(A15="","",IF(N(E15)=0,"n/a",G15/E15)) | K15: =IF(A15="","",IF(H15="n/a","n/a - no plan",IF(I15="Higher is better",IF(H15<-J15,"ALERT - below plan beyond threshold",IF(H15<0,"Below plan - within threshold","On or above plan")),IF(H15>J15,"ALERT - above plan beyond threshold",IF(H15>0,"Above plan - within threshold","On or below plan")))))
G16: =IF(A16="","",F16-E16) | H16: =IF(A16="","",IF(N(E16)=0,"n/a",G16/E16)) | K16: =IF(A16="","",IF(H16="n/a","n/a - no plan",IF(I16="Higher is better",IF(H16<-J16,"ALERT - below plan beyond threshold",IF(H16<0,"Below plan - within threshold","On or above plan")),IF(H16>J16,"ALERT - above plan beyond threshold",IF(H16>0,"Above plan - within threshold","On or below plan")))))
G17: =IF(A17="","",F17-E17) | H17: =IF(A17="","",IF(N(E17)=0,"n/a",G17/E17)) | K17: =IF(A17="","",IF(H17="n/a","n/a - no plan",IF(I17="Higher is better",IF(H17<-J17,"ALERT - below plan beyond threshold",IF(H17<0,"Below plan - within threshold","On or above plan")),IF(H17>J17,"ALERT - above plan beyond threshold",IF(H17>0,"Above plan - within threshold","On or below plan")))))
A19: Lines in ALERT status (notified automatically to the Planning Department Head) | K19: =COUNTIF(K6:K17,"ALERT*") -> 3
A21: NOTES FOR DEVELOPERS
A22: 1. For financial lines actuals are pulled automatically from Finance, Inventory, Sales and Procurement through the linked CoA sub-accounts; for operational lines they are the manual entries from PL-05. Variance = Actual - Planned, in absolute terms and as a percentage.
A23: 2. Direction drives the alert: volumes and revenues alert when they fall short by more than the threshold; costs and CAPEX alert when they overrun. Threshold values are parameters (PL-07).
A24: 3. Available in real time for any Second Unit, department, time period or plan category.

Sheet PL-07 Alert Parameters & Log
A1: [Corporation logo] | C1: NORTH COAL STATE OWNED CORPORATION
C2: VARIANCE ALERT PARAMETERS AND ALERT LOG
C3: Parameters are defined by the Planning Department; alerts go automatically to the Planning Department Head
A5: A. THRESHOLD PARAMETERS
A6: No. | B6: Plan Category / Metric | C6: Direction | D6: Alert Threshold % | E6: Source | F6: Notes
A7: 1 | B7: Coal extraction (tonnes) | C7: Higher is better | D7: 0.1 | E7: Report example (10%) | F7: Alert when actual extraction falls below plan by more than 10%.
A8: 2 | B8: Overburden excavation (m3) | C8: Higher is better | D8: 0.1 | E8: Illustrative - confirm | F8: Not specified in the report.
A9: 3 | B9: Main Core Revenue | C9: Higher is better | D9: 0.1 | E9: Illustrative - confirm | F9: Not specified in the report.
A10: 4 | B10: Non-Core Revenue | C10: Higher is better | D10: 0.1 | E10: Illustrative - confirm | F10: Not specified in the report.
A11: 5 | B11: Direct Costs | C11: Lower is better | D11: 0.15 | E11: Illustrative - confirm | F11: Report says "a defined limit"; no figure given.
A12: 6 | B12: Indirect Costs | C12: Lower is better | D12: 0.15 | E12: Illustrative - confirm | F12: Not specified in the report.
A13: 7 | B13: CAPEX | C13: Lower is better | D13: 0.1 | E13: Illustrative - confirm | F13: Not specified in the report.
A15: B. ALERT LOG (real-time; permanent)
A16: No. | B16: Date Generated | C16: Class / Plan Line | D16: Variance % | E16: Threshold / Status | F16: Head Review and Management Action
A17: 1 | B17: 46326.75 | C17: Second Unit A / Coal extraction | D17: -14.5% | E17: Threshold 10% - OPEN | F17: (awaiting Head review)
A18: 2 | B18: 46326.75 | C18: Second Unit A / Coal Sales Revenue | D18: -14.0% | E18: Threshold 10% - OPEN | F18: (awaiting Head review)
A19: 3 | B19: 46326.75 | C19: Second Unit A / Wood for excavation holes | D19: +24.0% | E19: Threshold 15% - REVIEWED | F19: Head reviewed 02-Nov; supplier price increase confirmed (example)
A20: 4
A21: 5
A22: 6
A24: NOTES FOR DEVELOPERS
A25: 1. Alerts are generated automatically when actual figures deviate from plan by more than the threshold, so management can intervene before profitability is hit; the Head receives them and takes management action.
A26: 2. The report gives one example (extraction more than 10% below plan) and says costs alert beyond "a defined limit"; every other value above is illustrative and must be confirmed. Dates and figures are example data.

Sheet PL-08 Actual vs Planned P&L
A1: [Corporation logo] | C1: NORTH COAL STATE OWNED CORPORATION
C2: ACTUAL VS PLANNED PROFIT AND LOSS
C3: Real-time report - planned figures come from PL-04; actuals pulled live from Finance, Sales and Inventory
A5: Fiscal Year | B5: FY-2026 | C5: Period | D5: January to September 2026 (YTD)
A6: Scope | B6: Consolidated (or any single Class) | C6: Generated On / By | D6: 14-Oct-2026 10:15 / PLN-HEAD-01
A8: Line | B8: Planned (AFN) | C8: Actual (AFN) | D8: Variance (AFN) | E8: Variance % | F8: Favourable?
A9: Main Core Revenue | B9: =SUMPRODUCT(('PL-04 Financial Plan'!$C$8:$C$19="Main Core Revenue")*'PL-04 Financial Plan'!$E$8:$M$19) -> 38700000 | C9: 35400000 | D9: =C9-B9 -> -3300000 | E9: =IF(B9=0,"n/a",D9/B9) -> -0.085271318 | F9: =IF(D9=0,"On plan",IF(D9>0,"Favourable","Unfavourable")) -> Unfavourable
A10: Non-Core Revenue | B10: =SUMPRODUCT(('PL-04 Financial Plan'!$C$8:$C$19="Non-Core Revenue")*'PL-04 Financial Plan'!$E$8:$M$19) -> 900000 | C10: 900000 | D10: =C10-B10 -> 0 | E10: =IF(B10=0,"n/a",D10/B10) -> 0 | F10: =IF(D10=0,"On plan",IF(D10>0,"Favourable","Unfavourable")) -> On plan
A11: TOTAL REVENUE | B11: =B9+B10 -> 39600000 | C11: =C9+C10 -> 36300000 | D11: =C11-B11 -> -3300000 | E11: =IF(B11=0,"n/a",D11/B11) -> -0.083333333 | F11: =IF(D11=0,"On plan",IF(D11>0,"Favourable","Unfavourable")) -> Unfavourable
A12: Less: Direct Costs | B12: =SUMPRODUCT(('PL-04 Financial Plan'!$C$8:$C$19="Direct Cost")*'PL-04 Financial Plan'!$E$8:$M$19) -> 6529500 | C12: 6900000 | D12: =C12-B12 -> 370500 | E12: =IF(B12=0,"n/a",D12/B12) -> 0.056742476 | F12: =IF(D12=0,"On plan",IF(D12<0,"Favourable","Unfavourable")) -> Unfavourable
A13: GROSS PROFIT | B13: =B11-B12 -> 33070500 | C13: =C11-C12 -> 29400000 | D13: =C13-B13 -> -3670500 | E13: =IF(B13=0,"n/a",D13/B13) -> -0.11099016 | F13: =IF(D13=0,"On plan",IF(D13>0,"Favourable","Unfavourable")) -> Unfavourable
A14: Less: Indirect Costs | B14: =SUMPRODUCT(('PL-04 Financial Plan'!$C$8:$C$19="Indirect Cost")*'PL-04 Financial Plan'!$E$8:$M$19) -> 4995000 | C14: 4850000 | D14: =C14-B14 -> -145000 | E14: =IF(B14=0,"n/a",D14/B14) -> -0.029029029 | F14: =IF(D14=0,"On plan",IF(D14<0,"Favourable","Unfavourable")) -> Favourable
A15: NET PROFIT / (LOSS) | B15: =B13-B14 -> 28075500 | C15: =C13-C14 -> 24550000 | D15: =C15-B15 -> -3525500 | E15: =IF(B15=0,"n/a",D15/B15) -> -0.12557212 | F15: =IF(D15=0,"On plan",IF(D15>0,"Favourable","Unfavourable")) -> Unfavourable
A17: Memo: CAPEX (outside the P&L) | B17: =SUMPRODUCT(('PL-04 Financial Plan'!$C$8:$C$19="CAPEX")*'PL-04 Financial Plan'!$E$8:$M$19) -> 6000000 | C17: 6250000 | D17: =C17-B17 -> 250000 | E17: =IF(B17=0,"n/a",D17/B17) -> 0.041666667 | F17: =IF(D17=0,"On plan",IF(D17<0,"Favourable","Unfavourable")) -> Unfavourable
A19: NOTES FOR DEVELOPERS
A20: 1. Actual revenue, cost and CAPEX figures are pulled live from the linked CoA sub-accounts; here they are grey example inputs. Planned figures are summed from the approved financial plan for the months selected (January-September).
A21: 2. Variance = Actual - Planned. For revenue and profit lines a positive variance is favourable; for cost and CAPEX lines a negative variance is favourable. The Head can filter by any Class, department, period or plan category.
A22: 3. The Head prints these reports for physical distribution to Directors and the ED (the ED has no system access).

Sheet PL-09 Plan Amendment Request
A1: [Corporation logo] | C1: NORTH COAL STATE OWNED CORPORATION
C2: PLAN AMENDMENT REQUEST
C3: Form PL-09 | Version 1.0 | Physical ED approval comes FIRST; the Officer then records it in the system
A5: A. AMENDMENT DETAILS
A6: Amendment No. (auto) | C6: AMD-2026-000003 | D6: Date Submitted | E6: 46307
A7: Original Plan Ref. | C7: PLN-2026-OP-01 | D7: Class | E7: Second Unit A
A8: Plan Item / Metric | C8: Extraction (raw coal) | D8: Nature of Amendment | E8: Physical (volumes)
A9: Reason for Amendment | C9: Natural event (flooding of the access road) limits extraction in the remaining months. EXAMPLE DATA.
A11: B. REVISED FIGURES
A12: No. | B12: Month | C12: Plan Item / Metric | D12: Original Figure | E12: Revised Figure | F12: Difference
A13: 1 | B13: Oct | C13: Extraction (raw coal) - tonnes | D13: 5500 | E13: 4800 | F13: =IF(B13="","",E13-D13) -> -700
A14: 2 | B14: Nov | C14: Extraction (raw coal) - tonnes | D14: 5000 | E14: 4200 | F14: =IF(B14="","",E14-D14) -> -800
A15: 3 | B15: Dec | C15: Extraction (raw coal) - tonnes | D15: 4500 | E15: 4000 | F15: =IF(B15="","",E15-D15) -> -500
A16: 4 | F16: =IF(B16="","",E16-D16)
A17: 5 | F17: =IF(B17="","",E17-D17)
A18: 6 | F18: =IF(B18="","",E18-D18)
A19: TOTAL | D19: =SUM(D13:D18) -> 15000 | E19: =SUM(E13:E18) -> 13000 | F19: =SUM(F13:F18) -> -2000
A21: C. APPROVAL
A22: ED Physical Approval Ref. (mandatory) | C22: ED-AMD-2026-0011 | D22: Date of ED Physical Approval | E22: 46305
A23: Supporting Justification | C23: Engineering assessment of access road damage; ED approval letter on file. EXAMPLE DATA.
A24: Planning Dept Head Decision | C24: Approved | D24: Decision Date | E24: 46308
A25: System Result | C25: =IF(C22="","BLOCKED - the ED physical approval reference is mandatory",IF(C23="","BLOCKED - supporting justification is mandatory",IF(C24="Approved","Revised figures activated in the comparative analysis; ORIGINAL figures retained for history and audit; Control Log updated","Not approved - original plan stays in force"))) -> Revised figures activated in the comparative analysis; ORIGINAL figures retained for history and audit; Control Log updated
A27: INITIATED BY (Planning Officer) | D27: APPROVED BY (Planning Department Head)
A28: Name: | D28: Name:
A29: Position: | D29: Position:
A30: Signature: | D30: Signature:
A31: Date: | D31: Date:
A33: NOTES FOR DEVELOPERS
A34: 1. The ED approves the amendment on paper outside the system; the Officer then submits this request recording the original plan reference, nature and reason, revised figures, the ED approval reference (mandatory) and justification.
A35: 2. The Head verifies that the system request matches the physical ED approval before approving. Revised figures replace the original in variance analysis; original figures stay in the system permanently and the Plan Amendment Log lists both.
A36: 3. Officers cannot approve their own amendments. ED field reference only - no ED signature block. Name, position and date may be pre-filled by the system from the Control Log; signatures are by hand so the printed form can be archived in the hard file.

Sheet PL-10 Correspondence Register
A1: [Corporation logo] | C1: NORTH COAL STATE OWNED CORPORATION
C2: OFFICIAL CORRESPONDENCE REGISTER (ADDITION)
C3: Replaces the physical in/out ledgers and carton archives - addition to the approved design
A5: ADDITION TO CONFIRM: the As-Is activity and pain point "lost documents and slow retrieval of official correspondence" have no matching feature in the To-Be. This register is proposed to close it.
A6: Reference No. | B6: Date | C6: Direction | D6: From / To | E6: Subject | F6: Responsible Department | G6: Hard-Copy File / Carton Ref. | H6: Status | I6: Logged By
A7: COR-2026-0412 | B7: 46300 | C7: Incoming | D7: Ministry of Mines and Petroleum | E7: Request for the quarterly production report | F7: Planning & Policy | G7: CARTON-2026-Q4-07 | H7: Open | I7: PLN-OFF-01
A8: COR-2026-0413 | B8: 46303 | C8: Outgoing | D8: General Directorate of State-Owned Corporations | E8: Monthly royalty and payment report | F8: Planning & Policy | G8: CARTON-2026-Q4-07 | H8: Closed | I8: PLN-OFF-01
A9: COR-2026-0414 | B9: 46304 | C9: Incoming | D9: Directorate of Administrative Affairs | E9: Annual plan clarification request | F9: Planning & Policy | G9: CARTON-2026-Q4-08 | H9: Open | I9: PLN-OFF-02

Sheet PL-11 Correction Request
A1: [Corporation logo] | C1: NORTH COAL STATE OWNED CORPORATION
C2: OFFICER CORRECTION REQUEST - PLANNING AND POLICY
C3: Form PL-11 | Version 1.0 | Same standard form as FA-11, module set to Planning and Policy
A5: A. REQUEST (raised by Planning Officer)
A6: Request No. | C6: CR-2026-000075 | D6: Date Raised | E6: 46307.375
A7: Module | C7: Planning and Policy | D7: Second Unit / HQ | E7: HQ
A8: Entry Type | C8: Actual operational volume | D8: Entry Reference | E8: PL-05 row 5 - Second Unit C excavation Oct-2026
A9: Raised By (Officer) | C9: PLN-OFF-01 | D9: Entry Status at Request | E9: Submitted
A10: Description of Error (written justification) | C10: Actual excavation keyed as 40,000 m3; the signed site report shows 4,000 m3. EXAMPLE DATA.
A11: Required Correction | C11: Change actual volume from 40,000 to 4,000 cubic metres.
A13: B. PLANNING DEPARTMENT HEAD DECISION (notified automatically on submission)
A14: Decision | C14: Approved | D14: Decision Date / Time | E14: 46307.403
A15: Reason (recorded if Rejected)
A16: Entry Unlocked | C16: Yes - Officer notified automatically | D16: Corrected Entry Ref. | E16: PL-05 row 5 (rev. 2)
A18: C. CONTROL LOG - PERMANENTLY RECORDED AND VISIBLE TO INTERNAL CONTROL
A19: Original entry | D19: Recorded
A20: Correction request | D20: Recorded
A21: Department Head approval | D21: Recorded
A22: Corrected entry | D22: Recorded
A24: REQUESTED BY (Planning Officer) | D24: DECIDED BY (Planning Department Head)
A25: Name: | D25: Name:
A26: Position: | D26: Position:
A27: Signature: | D27: Signature:
A28: Date: | D28: Date:
A30: NOTES FOR DEVELOPERS
A31: 1. Applies to a submitted plan entry (before finalization) or a manually entered actual volume. The Officer can never modify or delete a submitted entry directly. Every step is written to the Control Log (layout FA-18).

Sheet PL-12 Approval Matrix
A1: [Corporation logo] | C1: NORTH COAL STATE OWNED CORPORATION
C2: PLANNING AND POLICY APPROVAL MATRIX
C3: Who prepares and approves each form; the Executive Director has no system role
A5: Form | B5: Initiated / Prepared By | C5: Department Head Action | D5: ED / Directors (physical, outside system) | E5: Data Source | F5: Automatic System Action
A6: PL-01 Plan Item Creation | B6: Planning Officer | C6: Reviews as part of plan approval | D6: None | E6: Chart of Accounts (Finance) | F6: Links to CoA sub-account or N/A
A7: PL-02 / PL-03 / PL-04 Annual Plans | B7: Planning Officer (all Second Units and HQ) | C7: Approves; verifies against physical ED approval | D7: Reviews and approves annual plans physically | E7: Manual plan entry | F7: Plan becomes Active; planned P&L generated
A8: PL-05 Actual Volume Entry | B8: Planning Officer (verified site reports) | C8: None | D8: None | E8: Signed site reports (physical) | F8: Reference document mandatory; no GL impact
A9: PL-06 / PL-08 Variance and P&L | B9: System | C9: Full real-time access; generates and prints reports | D9: Receive printed reports | E9: Finance, Sales, Inventory, Procurement | F9: Variance abs and %; live Actual vs Planned P&L
A10: PL-07 Alerts | B10: System | C10: Receives alerts and takes action | D10: None | E10: Variance engine | F10: Alert when variance exceeds threshold
A11: PL-09 Plan Amendment | B11: Planning Officer (after physical ED approval) | C11: Approves against the ED document | D11: Approves amendment physically BEFORE entry | E11: Manual | F11: Revised figures activate; originals retained
A12: PL-11 Correction Request | B12: Planning Officer | C12: Approves / rejects; unlocks if approved | D12: None | E12: n/a | F12: Notifies Officer on unlock; logs every step

Sheet PL-13 Data Sources & Logic
A1: [Corporation logo] | C1: NORTH COAL STATE OWNED CORPORATION
C2: DATA SOURCES AND SYSTEM LOGIC - DEVELOPER REFERENCE
C3: The module posts NO accounting entries - it reads actuals and compares them with plan
A5: Plan Item Type | B5: Source of Actual Data | C5: Mechanism | D5: Notes
A6: Main Core Revenue (coal sales) | B6: Finance revenue accounts fed by Sales dispatch events | C6: Automatic pull by CoA sub-account per Class | D6: Revenue recognized on dispatch (FA-08, SM-07)
A7: Non-Core Revenue (rental income, scrap sales) | B7: Finance / Properties rental income and other income accounts | C7: Automatic pull by CoA sub-account | D7: Rental income per PP-05
A8: Direct Costs | B8: Finance, Inventory and Procurement expense accounts | C8: Automatic pull by CoA sub-account | D8: Includes wages, mining consumables
A9: Indirect Costs | B9: Finance expense accounts | C9: Automatic pull by CoA sub-account | D9: HQ administration, office supplies
A10: CAPEX | B10: Fixed-asset additions (Inventory, Properties, Procurement) | C10: Automatic pull by CoA sub-account | D10: Not part of the P&L
A11: Operational volumes (extraction tonnes, excavation m3) | B11: Signed site extraction / excavation reports | C11: Manual entry by Planning Officer with mandatory reference document | D11: CoA linkage = N/A; no GL impact
A13: SYSTEM LOGIC
A14: 1. Variance (absolute) = Actual - Planned; Variance % = Variance / Planned; both in real time for any Class, department, period or plan category.
A15: 2. Alerts: when the variance exceeds the defined threshold % in the unfavourable direction, an automatic alert goes to the Planning Department Head (PL-07).
A16: 3. Plan approval: Officer enters, Head approves, plan Active. Amendments need prior physical ED approval and a recorded reference; originals are retained permanently.
A17: 4. IAS 1 / ISO 9001 compliance statements in the approved report. IFRS 18 replaces IAS 1 for annual periods beginning 1 January 2027 - the comparative statement layout should allow for it.
A19: AS-IS ACTIVITIES NOT CARRIED INTO THE TO-BE (CONFIRM WITH THE REPORT OWNER)
A20: 1. Verifying monthly production and excavation data to authorize piece-rate payroll for contract mine workers (no link to the wages-based entry in Payroll).
A21: 2. Calculating and submitting the monthly coal royalty and payment report to Finance, the Ministry of Mines and Petroleum and the General Directorate of State-Owned Corporations (no royalty accrual or report in any module).
A22: 3. Preparing the mandatory quarterly operational, evaluation and financial realization reports for government bodies.
A23: 4. Drafting plans from topographical survey maps, and managing the contracting out of informally mined areas.
A24: 5. Logging official correspondence (a register is proposed in PL-10).

Sheet PL-14 Reports Spec
A1: [Corporation logo] | C1: NORTH COAL STATE OWNED CORPORATION
C2: REQUIRED REPORTS - PLANNING AND POLICY
C3: Real-time with a flexible Custom Date Range filter; header shows corporation name and logo, title, fiscal year, date range, timestamp and user
A5: # | B5: Report | C5: Frequency | D5: Filter Options | E5: Export
A6: 1 | B6: Annual Operational Plan Report | C6: On demand | D6: By Class (Second Unit), per physical metric (Excavation m3 / Extraction tonnes), per month/year | E6: PDF + Excel
A7: 2 | B7: Annual Financial Plan Report | C7: On demand | D7: By Class (Second Unit/HQ), by Category (Direct Cost, Indirect Cost, Revenue, CAPEX), per month/year | E7: PDF + Excel
A8: 3 | B8: Actual vs Planned Profit & Loss | C8: Real-time | D8: By Class (specific Second Unit or Consolidated); all revenues minus costs with variance % | E8: PDF + Excel
A9: 4 | B9: Operational Variance Report (Volumes) | C9: Monthly / On demand | D9: Per Second Unit, per period - physical variance (tonnes / m3) and percentage | E9: PDF + Excel
A10: 5 | B10: Financial Variance Report (AFN) | C10: Monthly / On demand | D10: Per Class, per CoA mapping, per period - AFN variance and percentage | E10: PDF + Excel
A11: 6 | B11: Consolidated Variance Summary | C11: Quarterly / Annual | D11: All Second Units and HQ - consolidated operational and financial variance across all categories | E11: PDF + Excel
A12: 7 | B12: Variance Alert Log | C12: Real-time | D12: All active variance alerts exceeding the defined threshold parameters | E12: PDF + Excel
A13: 8 | B13: Plan Amendment Log | C13: On demand | D13: All amendments - original figures, revised figures, reason, ED approval reference, Head approval date | E13: PDF + Excel
A14: 9 | B14: Control Log / Audit Trail Report | C14: On demand | D14: By user, date and action type (including all officer correction request loops and unlocks) | E14: PDF + Excel
