Workbook

Sheet Index
A1: NORTH COAL STATE OWNED CORPORATION
A2: ERP FORMS & STANDARD TEMPLATES - PROCUREMENT MODULE
A3: Developer pack accompanying the approved System Architecture & BPR Report (20 September 2026) | Prepared by Crest Point Consulting Group | Version 1.0
A5: COLOUR LEGEND
A6: Yellow | B6: Field entered by a user (blue text = example data shown for illustration)
A7: Grey | B7: Auto-populated / auto-calculated by the system
A8: Light grey | B8: Not applicable on this form
A9: Navy | B9: Section / column headers and signature-block titles
A11: Form Code | B11: Sheet (click to open) | C11: Purpose | D11: Source in approved report
A12: PC-01 | B12: PC-01 Pending Request Queue | C12: Queue of approved purchase requests with the ED approval gate | D12: 4.6.2 Purchase Request Receipt
A13: PC-02 | B13: PC-02 Method & Classification | C13: Procurement method and classification record | D13: 4.6.2 Procurement Method Selection
A14: PC-03 | B14: PC-03 Bid Comparison | C14: Competing bids and mandatory selection justification | D14: 4.6.2 Bid Tracking and Supplier Selection Justification
A15: PC-04 | B15: PC-04 PO & Contract | C15: Purchase order / contract record with deadline, alerts and deposit flag | D15: 4.6.2 Purchase Order & Contract Recording
A16: PC-05 | B16: PC-05 Security Deposit Action | C16: Deposit receipt, refund authorization and forfeiture | D16: 4.6.2 Supplier Security Deposit Management
A17: PC-06 | B17: PC-06 Security Deposit Ledger | C17: Active, refunded and forfeited deposits | D17: 4.6.2; 4.6.4 Reports
A18: PC-07 | B18: PC-07 Implementation Tracker | C18: Implementation % tracker with deadline alerts and Overdue / Breached flag | D18: 4.6.2 Project Implementation Tracking
A19: PC-08 | B19: PC-08 Extension Request | C19: Formal contract extension with mandatory justification | D19: 4.6.2 Contract Extension Workflow
A20: PC-09 | B20: PC-09 Project Handover | C20: Completion / handover record for non-goods contracts | D20: 4.6.2 Goods Delivery, Project Handover
A21: PC-10 | B21: PC-10 IC Verification | C21: Mandatory IC verify / reject at GRN or Handover | D21: 4.6.2 IC Verification Gate; Workflow 4
A22: PC-11 | B22: PC-11 Contract Register | C22: Register layout with summaries by method and status | D22: 4.6.4 Required Reports
... A29: PC-18 | B29: PC-18 Reports Spec | C29: Required procurement reports and filters | D29: 4.6.4 Required Reports
A31: DESIGN RULES THAT APPLY TO EVERY FORM
A32: 1. Single currency: Afghan Afghani (AFN) only.
A33: 2. The ERP does NOT run the procurement procedures: supplier selection, tendering, quotations and negotiation happen in hard copy outside the ERP and are referenced by document number. The ERP records the method, classification, bids, contract, deadlines, deposits and handover.
A34: 3. No purchase request is accessible to Procurement until the ED physical approval confirmation is recorded; requests without it stay in Pending ED Approval.
A35: 4. Internal Control verification is positioned strictly at the GRN or Project Handover stage; IC is otherwise read-only. Procurement forms therefore carry a "Verified by" block only on the handover and IC records.
A36: 5. The Executive Director and Directors have no system access; their approvals are physical and recorded by department staff. No ED / Director signature block appears on any printed form.
A37: 6. Officers can never edit or delete a submitted entry; corrections follow PC-15. Every action is written to the Control Log (layout FA-18 in the Finance workbook), which no user can alter.
A38: 7. Names, references, values and thresholds in these sheets are illustrative examples; threshold values come from the As-Is analysis and must be confirmed.

Sheet PC-01 Pending Request Queue
A1: [Corporation logo] | C1: NORTH COAL STATE OWNED CORPORATION
C2: PENDING PURCHASE REQUESTS QUEUE (ED APPROVAL GATE)
C3: Real-time queue - a request is accessible to Procurement only after the ED physical approval confirmation is recorded
A5: Purchase Request Ref. | B5: Requesting Department | C5: Item Description and Quantity Required | D5: Date of Request | E5: Dept Head Approval | F5: Director Physical Approval Recorded | G5: ED Physical Approval Confirmation Recorded | H5: Queue Status (auto) | I5: Accessible to Procurement Officer?
A6: PR-2026-0312 | B6: Inventory & Warehouse | C6: Diesel fuel - generators; 10,000 litres | D6: 46303 | E6: Approved | F6: Yes | G6: Yes | H6: =IF(A6="","",IF(AND(E6="Approved",F6="Yes",G6="Yes"),"Active queue","Pending ED Approval")) -> Active queue | I6: =IF(A6="","",IF(H6="Active queue","Yes","No - held")) -> Yes
A7: PR-2026-0318 | B7: Properties | C7: Roof repair materials - Block A; 1 lot | D7: 46304 | E7: Approved | F7: Yes | G7: No | H7: =IF(A7="","",IF(AND(E7="Approved",F7="Yes",G7="Yes"),"Active queue","Pending ED Approval")) -> Pending ED Approval | I7: =IF(A7="","",IF(H7="Active queue","Yes","No - held")) -> No - held
A8: PR-2026-0321 | B8: Administration | C8: Office chairs; 20 pieces | D8: 46307 | E8: Approved | F8: Yes | G8: Yes | H8: =IF(A8="","",IF(AND(E8="Approved",F8="Yes",G8="Yes"),"Active queue","Pending ED Approval")) -> Active queue | I8: =IF(A8="","",IF(H8="Active queue","Yes","No - held")) -> Yes
A9: PR-2026-0325 | B9: Finance | C9: Laptop computers; 3 pieces | D9: 46308 | E9: Approved | F9: No | G9: No | H9: =IF(A9="","",IF(AND(E9="Approved",F9="Yes",G9="Yes"),"Active queue","Pending ED Approval")) -> Pending ED Approval | I9: =IF(A9="","",IF(H9="Active queue","Yes","No - held")) -> No - held
H10: =IF(A10="","",IF(AND(E10="Approved",F10="Yes",G10="Yes"),"Active queue","Pending ED Approval")) | I10: =IF(A10="","",IF(H10="Active queue","Yes","No - held"))
H11: =IF(A11="","",IF(AND(E11="Approved",F11="Yes",G11="Yes"),"Active queue","Pending ED Approval")) | I11: =IF(A11="","",IF(H11="Active queue","Yes","No - held"))
H12: =IF(A12="","",IF(AND(E12="Approved",F12="Yes",G12="Yes"),"Active queue","Pending ED Approval")) | I12: =IF(A12="","",IF(H12="Active queue","Yes","No - held"))
H13: =IF(A13="","",IF(AND(E13="Approved",F13="Yes",G13="Yes"),"Active queue","Pending ED Approval")) | I13: =IF(A13="","",IF(H13="Active queue","Yes","No - held"))
H14: =IF(A14="","",IF(AND(E14="Approved",F14="Yes",G14="Yes"),"Active queue","Pending ED Approval")) | I14: =IF(A14="","",IF(H14="Active queue","Yes","No - held"))
H15: =IF(A15="","",IF(AND(E15="Approved",F15="Yes",G15="Yes"),"Active queue","Pending ED Approval")) | I15: =IF(A15="","",IF(H15="Active queue","Yes","No - held"))
H16: =IF(A16="","",IF(AND(E16="Approved",F16="Yes",G16="Yes"),"Active queue","Pending ED Approval")) | I16: =IF(A16="","",IF(H16="Active queue","Yes","No - held"))
H17: =IF(A17="","",IF(AND(E17="Approved",F17="Yes",G17="Yes"),"Active queue","Pending ED Approval")) | I17: =IF(A17="","",IF(H17="Active queue","Yes","No - held"))
A19: Requests in active queue | D19: =COUNTIF(H6:H17,"Active queue") -> 2
A20: Requests held - Pending ED Approval | D20: =COUNTIF(H6:H17,"Pending ED Approval") -> 2
A22: NOTES FOR DEVELOPERS
A23: 1. Each request arrives with a notification and shows: reference, requesting department, item description and quantity, date of request, Department Head / Director approval status and ED approval status.
A24: 2. System gate: requests without the recorded ED physical approval confirmation are held in "Pending ED Approval" status and are NOT accessible to the Procurement Officer.
A25: 3. The Inventory section (4.2) lists only Department Head and Director approval before transfer, while this section requires the ED confirmation and the Finance section adds a budget check (FA-09). Confirm the single approval chain; the As-Is pain point "cumbersome pre-procurement approvals" is not reduced by the To-Be as written.
A26: 4. The Executive Director and Directors have no system access. Their purchase approval is obtained physically outside the ERP and recorded by department staff BEFORE the request reaches Procurement; no ED / Director signature block appears on these forms.

Sheet PC-02 Method & Classification
A1: [Corporation logo] | C1: NORTH COAL STATE OWNED CORPORATION
C2: PROCUREMENT METHOD AND CLASSIFICATION RECORD
C3: Form PC-02 | Version 1.0 | Recorded by the Procurement Officer; the procurement procedures themselves run in hard copy outside the ERP
A5: A. REQUEST AND METHOD
A6: Purchase Request Ref. | C6: PR-2026-0312 | D6: Requesting Department | E6: Inventory & Warehouse
A7: Item Description and Quantity | C7: Diesel fuel - generators; 10,000 litres | D7: Estimated Value (AFN) | E7: 420000
A8: Procurement Method | C8: Quotation-Based | D8: Procurement Classification | E8: Goods
A10: B. THRESHOLD CHECKS (see PC-14)
A11: Threshold-Suggested Method | C11: =IF(E7<='PC-14 Thresholds Config'!$C$8,"Direct Purchase",IF(AND('PC-14 Thresholds Config'!$C$10<>"",E7>='PC-14 Thresholds Config'!$C$10),"Tender","Quotation-Based")) -> Quotation-Based | D11: Method Consistent with Threshold? | E11: =IF(C8=C11,"Yes","NO - review method against threshold") -> Yes
A12: Approving Authority by Value | C12: =IF(E7<='PC-14 Thresholds Config'!$C$13,"Executive Director",IF(E7<='PC-14 Thresholds Config'!$C$14,"General Directorate","National Procurement Authority")) -> Executive Director | D12: Authority Approval Ref. (if above ED limit) (addition - see note 3) | E12: (not required at this value)
A14: C. DOCUMENTS
A15: Hard-Copy Document Ref. (tender / quotation file) | C15: PROC-HC-2026-0188 | D15: Recorded By (Procurement Officer) | E15: PRC-OFF-01
A16: Next Step | C16: =IF(C8="Direct Purchase","Record purchase order (PC-04) - no competing bids required","Record competing bids and written justification (PC-03), then the purchase order (PC-04)") -> Record competing bids and written justification (PC-03), then the purchase order (PC-04)
A18: RECORDED BY (Procurement Officer)
A19: Name:
A20: Position:
A21: Signature:
A22: Date:
A24: NOTES FOR DEVELOPERS
A25: 1. Methods: Tender (high value), Quotation-Based (minimum three quotations, medium value), Direct Purchase (single supplier, low value). Classification defaults: Goods, Consultancy, Non-Consultancy, Construction; the Procurement Head can add, edit or disable classes (PC-13).
A26: 2. The approved report says thresholds are "defined" but gives no figures; PC-14 uses the As-Is values (quotations above AFN 20,000, ED authority to 5M, General Directorate to 35M, above that the National Procurement Authority). The consistency check is a suggested control, not an approved feature.
A27: 3. ADDITION TO CONFIRM: contracts above the ED limit need General Directorate or National Procurement Authority approval, but the To-Be records only the ED approval. The authority approval reference field is added to trace that hard-copy approval.
A28: 4. All tendering, quotation collection, evaluation and negotiation stay in hard copy outside the ERP and are referenced by document number.

Sheet PC-03 Bid Comparison
A1: [Corporation logo] | C1: NORTH COAL STATE OWNED CORPORATION
C2: BID COMPARISON AND SELECTION JUSTIFICATION
C3: Form PC-03 | Version 1.0 | Mandatory for Tender and Quotation-Based purchases before the purchase order is finalized
A5: A. REFERENCE
A6: Purchase Request Ref. | C6: PR-2026-0312 | D6: Procurement Method | E6: Quotation-Based
A7: Classification | C7: Goods | D7: Minimum Bids Required (see note 2) | E7: =IF(E6="Direct Purchase",0,'PC-14 Thresholds Config'!$C$11) -> 3
A8: Number of Bids Recorded | C8: =COUNT(C12:C17) -> 4 | D8: Lowest Eligible Bid (AFN) (Active suppliers only) | E8: {=IF(COUNTIF(E12:E17,"Active")=0,"",MIN(IF(E12:E17="Active",C12:C17)))} -> 420000
A10: B. COMPETING BIDS
A11: No. | B11: Supplier Name | C11: Bid Price (AFN) | D11: Hard-Copy Document Ref. | E11: Supplier Status (auto) | F11: Price Rank (eligible)
A12: 1 | B12: Example Supplier Co. | C12: 420000 | D12: PROC-HC-2026-0188/1 | E12: =IF(B12="","",IFERROR(INDEX('PC-12 Supplier Master'!$F$7:$F$30,MATCH(B12,'PC-12 Supplier Master'!$B$7:$B$30,0)),"Not in supplier master")) -> Active | F12: =IF(C12="","",IF(E12<>"Active","Ineligible",COUNTIFS($E$12:$E$17,"Active",$C$12:$C$17,"<"&C12)+1)) -> 1
A13: 2 | B13: Example Supplier B | C13: 445000 | D13: PROC-HC-2026-0188/2 | E13: =IF(B13="","",IFERROR(INDEX('PC-12 Supplier Master'!$F$7:$F$30,MATCH(B13,'PC-12 Supplier Master'!$B$7:$B$30,0)),"Not in supplier master")) -> Active | F13: =IF(C13="","",IF(E13<>"Active","Ineligible",COUNTIFS($E$12:$E$17,"Active",$C$12:$C$17,"<"&C13)+1)) -> 3
A14: 3 | B14: Example Supplier C | C14: 438000 | D14: PROC-HC-2026-0188/3 | E14: =IF(B14="","",IFERROR(INDEX('PC-12 Supplier Master'!$F$7:$F$30,MATCH(B14,'PC-12 Supplier Master'!$B$7:$B$30,0)),"Not in supplier master")) -> Active | F14: =IF(C14="","",IF(E14<>"Active","Ineligible",COUNTIFS($E$12:$E$17,"Active",$C$12:$C$17,"<"&C14)+1)) -> 2
A15: 4 | B15: Example Barred Co. | C15: 400000 | D15: PROC-HC-2026-0188/4 | E15: =IF(B15="","",IFERROR(INDEX('PC-12 Supplier Master'!$F$7:$F$30,MATCH(B15,'PC-12 Supplier Master'!$B$7:$B$30,0)),"Not in supplier master")) -> Blacklisted | F15: =IF(C15="","",IF(E15<>"Active","Ineligible",COUNTIFS($E$12:$E$17,"Active",$C$12:$C$17,"<"&C15)+1)) -> Ineligible
A16: 5 | E16: =IF(B16="","",IFERROR(INDEX('PC-12 Supplier Master'!$F$7:$F$30,MATCH(B16,'PC-12 Supplier Master'!$B$7:$B$30,0)),"Not in supplier master")) | F16: =IF(C16="","",IF(E16<>"Active","Ineligible",COUNTIFS($E$12:$E$17,"Active",$C$12:$C$17,"<"&C16)+1))
A17: 6 | E17: =IF(B17="","",IFERROR(INDEX('PC-12 Supplier Master'!$F$7:$F$30,MATCH(B17,'PC-12 Supplier Master'!$B$7:$B$30,0)),"Not in supplier master")) | F17: =IF(C17="","",IF(E17<>"Active","Ineligible",COUNTIFS($E$12:$E$17,"Active",$C$12:$C$17,"<"&C17)+1))
A19: C. SELECTION AND JUSTIFICATION
A20: Winning Supplier | C20: Example Supplier Co. | D20: Winning Bid Price (AFN) | E20: =IFERROR(INDEX(C12:C17,MATCH(C20,B12:B17,0)),"") -> 420000
A21: Winning Supplier Status | C21: =IFERROR(INDEX(E12:E17,MATCH(C20,B12:B17,0)),"Not among bidders") -> Active | D21: Winner is the Lowest Bid? | E21: =IF(E20="","",IF(E20=E8,"Yes","No - justification must explain")) -> Yes
A22: Written Justification (mandatory) | C22: Lowest evaluated price and full technical compliance with the fuel specification. EXAMPLE DATA.
A23: Gate Result | C23: =IF(E6="Direct Purchase","Not required - Direct Purchase (no competitive process)",IF(C8<E7,"BLOCKED - minimum number of competing bids not recorded",IF(C20="","BLOCKED - winning supplier not selected",IF(C21<>"Active","BLOCKED - winning supplier is not an eligible (Active) supplier",IF(C22="","BLOCKED - written justification for the winning selection is mandatory","READY - bid comparison complete; the purchase order may be finalized"))))) -> READY - bid comparison complete; the purchase order may be finalized
A25: RECORDED BY (Procurement Officer)
A26: Name:
A27: Position:
A28: Signature:
A29: Date:
A31: NOTES FOR DEVELOPERS
A32: 1. The Officer records competing supplier names and submitted bid prices (AFN) and a mandatory written justification for the winning selection (e.g. lowest evaluated price, technical compliance). The system stores and displays this for transparency and audit visibility.
A33: 2. The approved report requires "minimum three quotations" for Quotation-Based purchases; it gives no minimum for Tenders (PC-14 parameter applies to both until confirmed).
A34: 3. ADDITION TO CONFIRM: the As-Is pain point "no vendor management system to flag blacklisted or barred companies" has no feature in the To-Be. The Supplier Status column and winner-eligibility check use the supplier master in PC-12 to cover it. Example Barred Co. shows a blacklisted bidder.

Sheet PC-04 PO & Contract
A1: [Corporation logo] | C1: NORTH COAL STATE OWNED CORPORATION
C2: PURCHASE ORDER / CONTRACT RECORD
C3: Form PC-04 | Version 1.0 | Drafted by the Procurement Officer; approved by the Procurement Department Head; sent to the supplier in hard copy
A5: A. ORDER DETAILS
A6: PO / Contract Ref. (auto, sequential) | C6: PO-2026-0051 | D6: Date of Purchase Order (system date) | E6: 46304
A7: Purchase Request Ref. (linked) | C7: PR-2026-0312 | D7: Procurement Method | E7: Quotation-Based
A8: Supplier Name | C8: Example Supplier Co. | D8: Item / Project Description (from approved request) | E8: Diesel fuel - generators
A9: Quantity Approved in Request | C9: 10000 | D9: Quantity Ordered | E9: 10000
A10: Quantity Variance (auto) | C10: =E9-C9 -> 0 | D10: Variance Note (mandatory if variance is not 0)
A11: Unit Price (AFN) | C11: 42 | D11: Total Value (AFN) Quantity x Unit Price | E11: =E9*C11 -> 420000
A12: Contract Deadline / Completion Date | C12: 46326 | D12: Custom Notification Threshold (days before deadline) | E12: 7
A13: Alert Date (auto) | C13: =C12-E12 -> 46319 | D13: Delivery / Project Location | E13: HQ Store
A14: Security Deposit Required? | C14: Yes | D14: Required Deposit Amount (AFN) | E14: 42000
A15: Hard-Copy Document Ref. | C15: PROC-HC-2026-0188 | D15: ED / Director Approval Ref. (auto-linked from request) | E15: DIR-APR-2026-0449
A16: Status | C16: Raised | D16: Check | E16: =IF(AND(C14="Yes",N(E14)<=0),"ERROR: deposit amount required",IF(AND(C10<>0,E10=""),"ERROR: variance note required","OK")) -> OK
A18: B. APPROVAL
A19: Procurement Dept Head Decision | C19: Approved | D19: Decision Date | E19: 46304
A20: Result | C20: =IF(C19="Approved","Finalized - purchase order sent to the supplier in hard copy outside the ERP; ERP keeps the digital record and status","Not finalized - Officer must correct (correction request PC-15)") -> Finalized - purchase order sent to the supplier in hard copy outside the ERP; ERP keeps the digital record and status
A22: PREPARED BY (Procurement Officer) | D22: APPROVED BY (Procurement Department Head)
A23: Name: | D23: Name:
A24: Position: | D24: Position:
A25: Signature: | D25: Signature:
A26: Date: | D26: Date:
A28: NOTES FOR DEVELOPERS
A29: 1. Status path: Raised -> Sent to Supplier -> Goods Received (set automatically when the Inventory GRN is confirmed) -> Completed (set automatically after IC verification). The Tracker may also flag a contract Overdue / Breached (PC-07).
A30: 2. Quantity comes from the approved request; any variance must be noted. Total value is auto-calculated and not editable. The custom notification threshold (e.g. 1 week, 2 months) drives the deadline alert.
A31: 3. Supplier Security Deposit: when "Yes" the required amount is recorded here and tracked through PC-05 / PC-06. ED approval is auto-linked from the purchase request.
A32: 4. The Executive Director and Directors have no system access. Their purchase approval is obtained physically outside the ERP and recorded by department staff BEFORE the request reaches Procurement; no ED / Director signature block appears on these forms.

Sheet PC-05 Security Deposit Action
A1: [Corporation logo] | C1: NORTH COAL STATE OWNED CORPORATION
C2: SUPPLIER SECURITY DEPOSIT - RECEIPT, REFUND, FORFEITURE
C3: Form PC-05 | Version 1.0 | Refund and forfeiture are authorized by the Procurement Department Head; Finance processes
A5: A. DETAILS
A6: Action Record No. | C6: SDA-2026-000011 | D6: Date | E6: 46309
A7: Contract Ref. | C7: CT-2026-009 | D7: Supplier | E7: Example Consultant Ltd
A8: Action | C8: Refund authorization | D8: Amount (AFN) | E8: 40000
A9: Deposit Required per Contract (AFN) | C9: 40000 | D9: Deposit Held Before Action (AFN) | E9: 40000
A10: Procurement Head Decision (refund / forfeiture) | C10: Approved | D10: Decision Date | E10: 46309
A11: Finance Processing Ref. (bank reconciliation / PV) | C11: PV-000131 | D11: Processed By (Finance Officer) | E11: FIN-OFF-02
A12: Reason / Breach Description (mandatory for forfeiture) | C12: Contract successfully completed; handover verified by IC. EXAMPLE DATA.
A14: B. AUTOMATIC ENTRY AND CHECKS
A15: Accounting Entry | C15: =IF(C8="Receipt confirmation","Dr Bank Account / Cr Supplier Security Deposit (Current Liability)",IF(C8="Refund authorization","Dr Supplier Security Deposit (Current Liability) / Cr Bank Account",IF(C8="Forfeiture authorization","Dr Supplier Security Deposit (Current Liability) / Cr Other Income Account (penalty revenue)",""))) -> Dr Supplier Security Deposit (Current Liability) / Cr Bank Account
A16: Amount Check | C16: =IF(C8="Receipt confirmation",IF(E8=C9,"Amount equals the deposit required","CHECK - differs from the deposit required"),IF(E8<=E9,"OK - within the deposit held","BLOCKED - exceeds the deposit held")) -> OK - within the deposit held
A17: Posting Status | C17: =IF(C8="Receipt confirmation","Posts on the Finance Officer's confirmed match in bank reconciliation (FA-06), linked to the contract",IF(C10<>"Approved","Not authorized - no posting",IF(AND(C8="Forfeiture authorization",C12=""),"BLOCKED - breach description required","Authorized - system posts the entry automatically"))) -> Authorized - system posts the entry automatically
A19: AUTHORIZED BY (Procurement Department Head) | D19: PROCESSED BY (Finance Officer)
A20: Name: | D20: Name:
A21: Position: | D21: Position:
A22: Signature: | D22: Signature:
A23: Date: | D23: Date:
A25: NOTES FOR DEVELOPERS
A26: 1. Receipt: supplier pays into the corporate bank account; the Finance Officer confirms the deposit in bank reconciliation and links it to the specific contract. No Head authorization is needed for receipt.
A27: 2. Refund: after successful completion the Head authorizes release and Finance processes the payment. Forfeiture: on supplier breach the Head authorizes and the system recognizes the penalty as Other Income.
A28: 3. Deposits are held as Current Liabilities; forfeitures accrue to Other Income without manual Finance journals.

Sheet PC-06 Security Deposit Ledger
A1: [Corporation logo] | C1: NORTH COAL STATE OWNED CORPORATION
C2: SUPPLIER SECURITY DEPOSIT LEDGER
C3: Report layout - active, refunded and forfeited deposits (forfeitures transferred to Other Income)
A5: Contract Ref. | B5: Supplier | C5: Description | D5: Deposit Required (AFN) | E5: Received (AFN) | F5: Refunded (AFN) | G5: Forfeited to Other Income (AFN) | H5: Balance Held (AFN) | I5: Status (auto)
A6: CT-2026-014 | B6: Example Supplier Co. | C6: Construction - warehouse extension | D6: 150000 | E6: 150000 | F6: 0 | G6: 0 | H6: =IF(A6="","",N(E6)-N(F6)-N(G6)) -> 150000 | I6: =IF(A6="","",IF(N(E6)=0,"Awaiting receipt",IF(N(G6)>0,"Forfeited",IF(H6=0,"Refunded","Active - held")))) -> Active - held
A7: CT-2026-009 | B7: Example Consultant Ltd | C7: Consultancy - safety study | D7: 40000 | E7: 40000 | F7: 40000 | G7: 0 | H7: =IF(A7="","",N(E7)-N(F7)-N(G7)) -> 0 | I7: =IF(A7="","",IF(N(E7)=0,"Awaiting receipt",IF(N(G7)>0,"Forfeited",IF(H7=0,"Refunded","Active - held")))) -> Refunded
A8: CT-2026-003 | B8: Example Supplier B | C8: Goods - spare parts | D8: 60000 | E8: 60000 | F8: 0 | G8: 60000 | H8: =IF(A8="","",N(E8)-N(F8)-N(G8)) -> 0 | I8: =IF(A8="","",IF(N(E8)=0,"Awaiting receipt",IF(N(G8)>0,"Forfeited",IF(H8=0,"Refunded","Active - held")))) -> Forfeited
A9: PO-2026-0051 | B9: Example Supplier Co. | C9: Goods - diesel fuel | D9: 42000 | E9: 0 | F9: 0 | G9: 0 | H9: =IF(A9="","",N(E9)-N(F9)-N(G9)) -> 0 | I9: =IF(A9="","",IF(N(E9)=0,"Awaiting receipt",IF(N(G9)>0,"Forfeited",IF(H9=0,"Refunded","Active - held")))) -> Awaiting receipt
H10: =IF(A10="","",N(E10)-N(F10)-N(G10)) | I10: =IF(A10="","",IF(N(E10)=0,"Awaiting receipt",IF(N(G10)>0,"Forfeited",IF(H10=0,"Refunded","Active - held"))))
H11: =IF(A11="","",N(E11)-N(F11)-N(G11)) | I11: =IF(A11="","",IF(N(E11)=0,"Awaiting receipt",IF(N(G11)>0,"Forfeited",IF(H11=0,"Refunded","Active - held"))))
H12: =IF(A12="","",N(E12)-N(F12)-N(G12)) | I12: =IF(A12="","",IF(N(E12)=0,"Awaiting receipt",IF(N(G12)>0,"Forfeited",IF(H12=0,"Refunded","Active - held"))))
H13: =IF(A13="","",N(E13)-N(F13)-N(G13)) | I13: =IF(A13="","",IF(N(E13)=0,"Awaiting receipt",IF(N(G13)>0,"Forfeited",IF(H13=0,"Refunded","Active - held"))))
H14: =IF(A14="","",N(E14)-N(F14)-N(G14)) | I14: =IF(A14="","",IF(N(E14)=0,"Awaiting receipt",IF(N(G14)>0,"Forfeited",IF(H14=0,"Refunded","Active - held"))))
H15: =IF(A15="","",N(E15)-N(F15)-N(G15)) | I15: =IF(A15="","",IF(N(E15)=0,"Awaiting receipt",IF(N(G15)>0,"Forfeited",IF(H15=0,"Refunded","Active - held"))))
A16: TOTAL | D16: =SUM(D6:D15) -> 292000 | E16: =SUM(E6:E15) -> 250000 | F16: =SUM(F6:F15) -> 40000 | G16: =SUM(G6:G15) -> 60000 | H16: =SUM(H6:H15) -> 150000
A18: NOTES FOR DEVELOPERS
A19: 1. Deposits held are Current Liabilities (Dr Bank / Cr Supplier Security Deposit); refunds clear the liability; forfeitures move it to Other Income. Balance Held = Received - Refunded - Forfeited.
A20: 2. The deposit received for CT-2026-014 matches the AFN 150,000 "supplier security deposit" example in the Finance bank reconciliation sheet (FA-06).

Sheet PC-07 Implementation Tracker
A1: [Corporation logo] | C1: NORTH COAL STATE OWNED CORPORATION
C2: PROJECT IMPLEMENTATION TRACKER AND DEADLINE ALERTS
C3: Form PC-07 | Version 1.0 | Large contracts (Construction, Consultancy) - updated by the Procurement Officer
A5: Contract Ref. | C5: CT-2026-014 | D5: Supplier / Contractor | E5: Example Supplier Co.
A6: Contract Deadline | C6: 46387 | D6: Notification Threshold (days before deadline) | E6: 30
A7: Report As-of Date | C7: 46309 | D7: Classification | E7: Construction
A9: No. | B9: Update Date | C9: Implementation % | D9: Basis (physical site report / milestone certificate ref.) | E9: Updated By | F9: Comment
A10: 1 | B10: 46204 | C10: 0.1 | D10: Site report SR-2026-031 | E10: PRC-OFF-01
A11: 2 | B11: 46235 | C11: 0.25 | D11: Site report SR-2026-044 | E11: PRC-OFF-01
A12: 3 | B12: 46266 | C12: 0.4 | D12: Milestone certificate MC-2026-006 | E12: PRC-OFF-01
A13: 4 | B13: 46296 | C13: 0.5 | D13: Milestone certificate MC-2026-007 | E13: PRC-OFF-01
A14: 5
A15: 6
A16: 7
A17: 8
A19: TRACKER SUMMARY (auto)
A20: Latest Implementation % | C20: =IF(COUNT(C10:C17)=0,0,LOOKUP(9.99E+307,C10:C17)) -> 0.5
A21: Days to Deadline | C21: =C6-C7 -> 78
A22: Alert Date | C22: =C6-E6 -> 46357
A23: Contract Status | C23: =IF(C20>=1,"Complete (100%)",IF(C7>C6,"OVERDUE / BREACHED",IF(C7>=C22,"ALERT - approaching deadline and implementation below 100% (notify Officer and Head)","On track"))) -> On track
A25: UPDATED BY (Procurement Officer) | D25: ALERTS RECEIVED BY (Procurement Department Head)
A26: Name: | D26: Name:
A27: Position: | D27: Position:
A28: Signature: | D28: Signature:
A29: Date: | D29: Date:
A31: NOTES FOR DEVELOPERS
A32: 1. The Officer periodically updates the implementation % (e.g. 25%, 50%, 75%) from physical site reports or milestone certificates. Automated alerts go to the Procurement Officer and Head when the deadline is near and the % is below 100%; a passed deadline flags the contract Overdue / Breached.
A33: 2. The alert threshold is the custom value set on the purchase order (PC-04). A formally approved extension (PC-08) updates the deadline and resets the alerts.

Sheet PC-08 Extension Request
A1: [Corporation logo] | C1: NORTH COAL STATE OWNED CORPORATION
C2: CONTRACT EXTENSION REQUEST
C3: Form PC-08 | Version 1.0 | Initiated by the Procurement Officer; approved by the Procurement Department Head
A5: Extension Request No. | C5: EXT-2026-000007 | D5: Date Raised | E5: 46309
A6: Contract Ref. | C6: CT-2026-014 | D6: Supplier / Contractor | E6: Example Supplier Co.
A7: Current Contract Deadline | C7: 46387 | D7: Proposed New Deadline | E7: 46418
A8: Extension Requested (days) | C8: =E7-C7 -> 31 | D8: Implementation % at Request | E8: 0.5
A9: Written Justification (mandatory) | C9: Winter weather delays to concrete works; supplier requests 31 days. EXAMPLE DATA.
A10: Procurement Head Decision | C10: Approved | D10: Decision Date | E10: 46310
A11: System Result | C11: =IF(C9="","BLOCKED - written justification is mandatory",IF(C10="Approved","Contract deadline updated to "&TEXT(E7,"dd-mmm-yyyy")&"; automated alerts reset","Request rejected - original deadline stays; Overdue / Breached flag applies if it passes")) -> Contract deadline updated to 31-Jan-2027; automated alerts reset
A14: REQUESTED BY (Procurement Officer) | D14: APPROVED BY (Procurement Department Head)
A15: Name: | D15: Name:
A16: Position: | D16: Position:
A17: Signature: | D17: Signature:
A18: Date: | D18: Date:
A20: NOTES FOR DEVELOPERS
A21: 1. Formal extension workflow: Officer enters the proposed new deadline and a mandatory written justification -> request goes to the Head -> on approval the system updates the contract deadline and resets the automated alerts. Every step is in the Control Log (FA-18).

Sheet PC-09 Project Handover
A1: [Corporation logo] | C1: NORTH COAL STATE OWNED CORPORATION
C2: PROJECT COMPLETION / HANDOVER RECORD (NON-GOODS CONTRACTS)
C3: Form PC-09 | Version 1.0 | Recorded by Requesting Department staff for Consultancy / Construction / services
A5: A. HANDOVER DETAILS
A6: Handover Record No. | C6: PH-2026-000009 | D6: Date Recorded | E6: 46301
A7: Contract Ref. | C7: CT-2026-009 | D7: Supplier / Consultant | E7: Example Consultant Ltd
A8: Classification | C8: Consultancy | D8: Requesting Department | E8: Planning & Policy
A9: Project / Service Description | C9: Mine safety consultancy study - final report delivered. EXAMPLE DATA.
A10: Completion Date | C10: 46300 | D10: Implementation % at Handover | E10: 1
A11: Completion / Milestone Certificate Ref. | C11: MC-2026-011 | D11: Supplier Invoice Ref. | E11: INV-C-0231
A12: Contract Value (AFN) | C12: 800000 | D12: Supplier Invoice Amount (AFN) | E12: 800000
A13: Recorded By (Requesting Dept staff) | C13: PLN-OFF-02 | D13: Status | E13: Pending IC verification
A14: Next Step | C14: Routed to Internal Control for mandatory verification (PC-10) before any accounting entry is posted or payment cleared.
A16: PREPARED BY (Requesting Department Staff) | D16: REVIEWED BY (Requesting Department Head) | E16: VERIFIED BY (Internal Control & Audit)
A17: Name: | D17: Name: | E17: Name:
A18: Position: | D18: Position: | E18: Position:
A19: Signature: | D19: Signature: | E19: Signature:
A20: Date: | D20: Date: | E20: Date:
A22: NOTES FOR DEVELOPERS
A23: 1. For non-goods contracts the requesting department - not Procurement - records the completion or handover. Goods are received by the Inventory department through the GRN (IN-05).
A24: 2. If Internal Control rejects, the Requesting Department Head unlocks the record, the staff corrects it and resubmits, the Head re-approves and it returns to IC.
A25: 3. Name, position and date may be pre-filled by the system from the Control Log; signatures are by hand so the printed form can be archived in the hard file.

Sheet PC-10 IC Verification
A1: [Corporation logo] | C1: NORTH COAL STATE OWNED CORPORATION
C2: INTERNAL CONTROL VERIFICATION - GRN OR PROJECT HANDOVER
C3: Form PC-10 | Version 1.0 | The only mandatory IC gate in the Procurement module (goods version also at IN-06)
A5: Verification No. | C5: ICV-2026-000445 | D5: Date Received by IC | E5: 46302
A6: Document Type | C6: Project Handover | D6: Document Ref. | E6: PH-2026-000009
A7: PO / Contract Ref. | C7: CT-2026-009 | D7: Re-verification Round | E7: 1
A8: Contract Value (AFN) | C8: 800000 | D8: Value Delivered / Completed (AFN) | E8: 800000
A9: Supplier Invoice Amount (AFN) | C9: 800000 | D9: Physical Delivery / Completion Confirmed by IC? | E9: Yes
A11: VERIFICATION CHECKS (system-assisted)
A12: No. | B12: Check | E12: Result | F12: IC Comment
A13: 1 | B13: Delivered goods / completed milestones exactly match the physical reality | E13: =E9 -> Yes
A14: 2 | B14: Delivered / completed value exactly matches the supplier invoice | E14: =IF(C8=E8,"Yes","No") -> Yes
A15: 3 | B15: Delivery / completion is consistent with the approved contract terms (value within contract) | E15: =IF(E8<=C8,"Yes","No") -> Yes
A16: Outcome (system rule) | C16: =IF(COUNTBLANK(E13:E15)>0,"INCOMPLETE",IF(COUNTIF(E13:E15,"No")>0,"REJECT","VERIFY")) -> VERIFY
A17: Final Outcome (IC decision) | C17: Verified | D17: Decision Date | E17: 46302
A18: IC Comments (mandatory if Rejected)
A19: If Rejected | C19: =IF(C6="Goods Receipt Note","Notification with IC comments to the Inventory Department Head -> Head unlocks -> Inventory Officer corrects and resubmits -> Head re-approves -> back to IC","Notification with IC comments to the Requesting Department Head -> Head unlocks -> staff corrects and resubmits -> Head re-approves -> back to IC") -> Notification with IC comments to the Requesting Department Head -> Head unlocks -> staff corrects and resubmits -> Head re-approves -> back to IC
A20: If Verified | C20: PO / contract status -> Completed; system posts Dr Relevant Expense or Fixed Asset Account / Cr Accounts Payable; Finance receives the "Awaiting Payment" notification for the final supplier payment.
A22: PREPARED BY (Inventory Officer / Requesting Dept Staff) | D22: REVIEWED BY (Receiving Department Head) | E22: VERIFIED BY (Internal Control & Audit)
A23: Name: | D23: Name: | E23: Name:
A24: Position: | D24: Position: | E24: Position:
A25: Signature: | D25: Signature: | E25: Signature:
A26: Date: | D26: Date: | E26: Date:
A28: NOTES FOR DEVELOPERS
A29: 1. IC verifies physical delivery / project completion against the supplier invoice and the approved contract terms. Read-only access; Verify or Reject only, comments mandatory on rejection; every outcome goes to the Control Log (FA-18).
A30: 2. Where goods are received through a GRN, the same verification is shown in IN-06 and the Procurement module simply follows the resulting status.
A31: 3. Name, position and date may be pre-filled by the system from the Control Log; signatures are by hand so the printed form can be archived in the hard file.

Sheet PC-11 Contract Register
A1: [Corporation logo] | C1: NORTH COAL STATE OWNED CORPORATION
C2: PURCHASE ORDER / CONTRACT REGISTER
C3: Report layout - status of every purchase order and contract
A5: Date Range | C5: 01-Jan-2026 to 31-Oct-2026 | F5: Generated On / By | G5: 14-Oct-2026 10:15 / PRC-HEAD-01
A7: PO / Contract Ref. | B7: Date | C7: Purchase Request Ref. | D7: Method | E7: Classification | F7: Supplier | G7: Total Value (AFN) | H7: Delivery Location | I7: Status | J7: Requesting Department
A8: PO-2026-0045 | B8: 46285 | C8: PR-2026-0298 | D8: Quotation-Based | E8: Goods | F8: Example Supplier Co. | G8: 85000 | H8: HQ Store | I8: Goods Received | J8: Inventory & Warehouse
A9: PO-2026-0051 | B9: 46304 | C9: PR-2026-0312 | D9: Quotation-Based | E9: Goods | F9: Example Supplier Co. | G9: 420000 | H9: HQ Store | I9: Sent to Supplier | J9: Inventory & Warehouse
A10: CT-2026-014 | B10: 46188 | C10: PR-2026-0187 | D10: Tender | E10: Construction | F10: Example Supplier Co. | G10: 3000000 | H10: HQ | I10: Sent to Supplier | J10: Properties
A11: CT-2026-009 | B11: 46144 | C11: PR-2026-0120 | D11: Quotation-Based | E11: Consultancy | F11: Example Consultant Ltd | G11: 800000 | H11: HQ | I11: Completed | J11: Planning & Policy
A12: CT-2026-003 | B12: 46063 | C12: PR-2026-0044 | D12: Tender | E12: Goods | F12: Example Supplier B | G12: 2000000 | H12: Second Unit A | I12: Overdue / Breached | J12: Inventory & Warehouse
A20: TOTAL VALUE (AFN) | G20: =SUM(G8:G19) -> 6305000
A22: SUMMARY BY METHOD | D22: Number | E22: Total Value (AFN) | H22: SUMMARY BY STATUS | J22: Number
A23: Tender | D23: =COUNTIF($D$8:$D$19,A23) -> 2 | E23: =SUMIF($D$8:$D$19,A23,$G$8:$G$19) -> 5000000 | H23: Raised | J23: =COUNTIF($I$8:$I$19,H23) -> 0
A24: Quotation-Based | D24: =COUNTIF($D$8:$D$19,A24) -> 3 | E24: =SUMIF($D$8:$D$19,A24,$G$8:$G$19) -> 1305000 | H24: Sent to Supplier | J24: =COUNTIF($I$8:$I$19,H24) -> 2
A25: Direct Purchase | D25: =COUNTIF($D$8:$D$19,A25) -> 0 | E25: =SUMIF($D$8:$D$19,A25,$G$8:$G$19) -> 0 | H25: Goods Received | J25: =COUNTIF($I$8:$I$19,H25) -> 1
H26: Completed | J26: =COUNTIF($I$8:$I$19,H26) -> 1
H27: Overdue / Breached | J27: =COUNTIF($I$8:$I$19,H27) -> 1
A29: NOTES FOR DEVELOPERS
A30: 1. Supports the reports on purchases by method (number and value), by classification, by supplier, by requesting department and by delivery location, and the status of all active purchase orders and contracts.
A31: 2. The four statuses in the approved design are Raised / Sent to Supplier / Goods Received / Completed; "Overdue / Breached" is the tracker flag from PC-07 and is shown here as a fifth status - confirm.

Sheet PC-12 Supplier Master
A1: [Corporation logo] | C1: NORTH COAL STATE OWNED CORPORATION
C2: SUPPLIER MASTER AND BLACKLIST REGISTER
C3: Addition to the approved design - covers the "no vendor management system" pain point
A5: ADDITION TO CONFIRM: the As-Is pain point asks for a database that records and flags blacklisted or barred companies, but the To-Be has no such feature. This layout is proposed; bid and winner eligibility checks in PC-03 read from it.
A6: Supplier ID | B6: Supplier Name | C6: Contact Person | D6: Phone | E6: Address | F6: Status | G6: Reason / Hard-Copy Reference | H6: Updated By
A7: SUP-0001 | B7: Example Supplier Co. | C7: Example Contact 1 | D7: +93 700 000 011 | E7: Example address, Kabul | F7: Active | H7: PRC-OFF-01
A8: SUP-0002 | B8: Example Supplier B | C8: Example Contact 2 | D8: +93 700 000 012 | E8: Example address, Kabul | F8: Active | H8: PRC-OFF-01
A9: SUP-0003 | B9: Example Supplier C | C9: Example Contact 3 | D9: +93 700 000 013 | E9: Example address, Herat | F9: Active | H9: PRC-OFF-01
A10: SUP-0004 | B10: Example Barred Co. | C10: Example Contact 4 | D10: +93 700 000 014 | E10: Example address, Kandahar | F10: Blacklisted | G10: Barred by decree DEC-2025-114 (example) | H10: PRC-HEAD-01
A11: SUP-0005 | B11: Example Consultant Ltd | C11: Example Contact 5 | D11: +93 700 000 015 | E11: Example address, Kabul | F11: Active | H11: PRC-OFF-01

Sheet PC-13 Classifications
A1: [Corporation logo] | C1: NORTH COAL STATE OWNED CORPORATION
C2: PROCUREMENT CLASSIFICATION SETTINGS
C3: Maintained by the Procurement Department Head in system settings
A5: No. | B5: Classification | C5: Type | D5: Status | E5: Changed On | F5: Changed By
A6: 1 | B6: Goods | C6: Default | D6: Active | E6: 46023 | F6: System
A7: 2 | B7: Consultancy | C7: Default | D7: Active | E7: 46023 | F7: System
A8: 3 | B8: Non-Consultancy | C8: Default | D8: Active | E8: 46023 | F8: System
A9: 4 | B9: Construction | C9: Default | D9: Active | E9: 46023 | F9: System
A10: 5 | B10: Equipment Lease (example) | C10: Custom | D10: Active | E10: 46174 | F10: PRC-HEAD-01
A11: 6
A12: 7
A13: 8
A14: 9
A15: 10
A17: NOTES FOR DEVELOPERS
A18: 1. Only the Procurement Department Head can add, edit or disable classifications. Disabled classes stay on historical records. Every change goes to the Control Log (FA-18).

Sheet PC-14 Thresholds Config
A1: [Corporation logo] | C1: NORTH COAL STATE OWNED CORPORATION
C2: PROCUREMENT THRESHOLDS AND AUTHORITY LIMITS (PARAMETERS)
C3: Parameter table - values from the As-Is analysis; confirm against Afghan public procurement rules for state-owned corporations
A7: No. | B7: Parameter | C7: Value | D7: Source | E7: Notes
A8: 1 | B8: Direct Purchase - upper limit (AFN) | C8: 20000 | D8: As-Is (inferred) | E8: Purchases up to this value need no competing quotes; inferred from "three quotes above 20,000".
A9: 2 | B9: Quotation-Based - applies above (AFN) | C9: 20000 | D9: As-Is | E9: Minimum three quotations obtained from suppliers and compared.
A10: 3 | B10: Tender threshold (AFN) | D10: NOT STATED - confirm | E10: The report says "defined tender threshold" but gives no figure. Leave blank until confirmed; the suggestion then never proposes Tender.
A11: 4 | B11: Minimum number of quotations / bids | C11: 3 | D11: To-Be: "minimum three quotations" | E11: Applied to Quotation-Based; assumed for Tender until confirmed.
A12: 5 | B12: Cash payment applies below (AFN) | C12: 50000 | D12: As-Is | E12: Cash for amounts under 50,000 AFN, bank transfer above. Applies to Finance payment mode.
A13: 6 | B13: Executive Director authority - up to (AFN) | C13: 5000000 | D13: As-Is | E13: Contracts up to this value are approved by the ED.
A14: 7 | B14: General Directorate authority - up to (AFN) | C14: 35000000 | D14: As-Is | E14: Above the ED limit and up to this value.
A15: 8 | B15: National Procurement Authority - above (AFN) | C15: =C14 -> 35000000 | D15: As-Is | E15: Contracts above the General Directorate limit.
A17: TEST CALCULATOR
A18: Contract value (AFN) | C18: 420000
A19: Suggested method | C19: =IF(C18<=C8,"Direct Purchase",IF(AND(C10<>"",C18>=C10),"Tender","Quotation-Based")) -> Quotation-Based
A20: Approving authority | C20: =IF(C18<=C13,"Executive Director",IF(C18<=C14,"General Directorate","National Procurement Authority")) -> Executive Director
A21: Payment mode (Finance) | C21: =IF(C18<C12,"Cash","Bank transfer") -> Bank transfer
A23: NOTES FOR DEVELOPERS
A24: 1. Rows 8-15 feed the consistency check on PC-02 and the minimum-bids rule on PC-03. They must be editable parameters (with effective dates in a real build) so procurement-rule changes need no code change.
A25: 2. The To-Be only ever records ED approval; it does not capture approval by the General Directorate or the National Procurement Authority for larger contracts (see PC-02 note 3).

Sheet PC-15 Correction Request
A1: [Corporation logo] | C1: NORTH COAL STATE OWNED CORPORATION
C2: OFFICER CORRECTION REQUEST - PROCUREMENT
C3: Form PC-15 | Version 1.0 | Same standard form as FA-11, module set to Procurement
A5: A. REQUEST (raised by Procurement Officer)
A6: Request No. | C6: CR-2026-000071 | D6: Date Raised | E6: 46304.597
A7: Module | C7: Procurement | D7: Second Unit / HQ | E7: HQ
A8: Entry Type | C8: Purchase Order / Contract | D8: Entry Reference | E8: PO-2026-0051
A9: Raised By (Officer) | C9: PRC-OFF-01 | D9: Entry Status at Request | E9: Submitted - before finalization
A10: Description of Error (written justification) | C10: Contract deadline entered as 31-Oct-2025; the contract states 31-Oct-2026. EXAMPLE DATA.
A11: Required Correction | C11: Change Contract Deadline to 31-Oct-2026.
A13: B. PROCUREMENT DEPARTMENT HEAD DECISION (notified automatically on submission)
A14: Decision | C14: Approved | D14: Decision Date / Time | E14: 46304.625
A15: Reason (recorded if Rejected)
A16: Entry Unlocked | C16: Yes - Officer notified automatically | D16: Corrected Entry Ref. | E16: PO-2026-0051 (rev. 2)
A18: C. CONTROL LOG - PERMANENTLY RECORDED AND VISIBLE TO INTERNAL CONTROL
A19: Original entry | D19: Recorded
A20: Correction request | D20: Recorded
A21: Department Head approval | D21: Recorded
A22: Corrected entry | D22: Recorded
A24: REQUESTED BY (Procurement Officer) | D24: DECIDED BY (Procurement Department Head)
A25: Name: | D25: Name:
A26: Position: | D26: Position:
A27: Signature: | D27: Signature:
A28: Date: | D28: Date:
A30: NOTES FOR DEVELOPERS
A31: 1. Applies to submitted records before finalization (e.g. wrong contract deadline, notification threshold or item description). The Officer can never modify or delete a submitted entry directly. An IC rejection at GRN / Handover uses the loop in PC-10. Every step is written to the Control Log.

Sheet PC-16 Approval Matrix
A1: [Corporation logo] | C1: NORTH COAL STATE OWNED CORPORATION
C2: PROCUREMENT APPROVAL AND VERIFICATION MATRIX
C3: Who prepares, approves and verifies each form; the Executive Director has no system role
A5: Form | B5: Initiated / Prepared By | C5: Department Head Action | D5: ED / Director (physical, outside system) | E5: Other Role | F5: Internal Control (read-only) | G5: Automatic System Action
A6: PC-01 Pending Queue | B6: Requesting department staff transfer approved request | C6: Requesting Dept Head approved earlier | D6: ED approval obtained outside, recorded by staff before transfer | E6: None | F6: Read-only | G6: Holds requests without ED confirmation in Pending ED Approval
A7: PC-02 Method & Classification | B7: Procurement Officer | C7: None (Head sets classifications) | D7: None | E7: None | F7: Read-only | G7: Threshold suggestion (recommended)
A8: PC-03 Bid Comparison | B8: Procurement Officer | C8: None | D8: None | E8: None | F8: Read-only | G8: Stores bids and justification; supplier eligibility check (addition)
A9: PC-04 PO & Contract | B9: Procurement Officer drafts | C9: Procurement Head approves and finalizes | D9: ED approval auto-linked from request | E9: None | F9: Read-only | G9: Auto total value; alert date; status Raised -> Sent
A10: PC-05 Security Deposit | B10: Finance confirms receipt; Procurement Head authorizes refund / forfeiture | C10: Authorizes refund and forfeiture | D10: None | E10: Finance Officer confirms receipt / processes refund | F10: Read-only | G10: Posts deposit, refund or forfeiture entry
A11: PC-07 Tracker / PC-08 Extension | B11: Procurement Officer updates % / raises extension | C11: Approves extension; receives alerts | D11: None | E11: None | F11: Read-only | G11: Alerts to Officer and Head; resets alerts on extension; flags Overdue / Breached
A12: PC-09 Project Handover | B12: Requesting Department staff | C12: Requesting Dept Head reviews and re-approves after rejection | D12: None | E12: None | F12: Mandatory Verify or Reject | G12: Routes to IC
A13: PC-10 IC Verification | B13: n/a | C13: Inventory Head or Requesting Dept Head unlocks on rejection | D13: None | E13: Finance receives Awaiting Payment | F13: Verify / Reject at GRN or Handover | G13: On verification: PO Completed; Dr Expense or Fixed Asset / Cr AP
A14: PC-13 Classifications | B14: Procurement Dept Head | C14: Adds / edits / disables | D14: None | E14: None | F14: Read-only | G14: Logs every change
A15: PC-15 Correction Request | B15: Procurement Officer | C15: Approves / rejects; unlocks if approved | D15: None | E15: None | F15: Sees full trail in Control Log | G15: Notifies Officer on unlock; logs every step

Sheet PC-17 Accounting Entries
A1: [Corporation logo] | C1: NORTH COAL STATE OWNED CORPORATION
C2: ACCOUNTING ENTRIES - DEVELOPER REFERENCE (PROCUREMENT)
C3: Posted automatically in the background - no manual journal entries by Finance
A5: # | B5: Trigger Event | C5: Debit | D5: Credit | E5: Posting Basis / Related Form
A6: 1 | B6: Supplier security deposit received (confirmed by Finance) | C6: Bank Account | D6: Supplier Security Deposit Account (Current Liability) | E6: Finance Officer confirms in bank reconciliation, linked to the contract (PC-05, FA-06)
A7: 2 | B7: Supplier security deposit refunded (processed by Finance) | C7: Supplier Security Deposit Account (Current Liability) | D7: Bank Account | E7: After Procurement Head authorization (PC-05)
A8: 3 | B8: Supplier security deposit forfeited (approved by Procurement Head) | C8: Supplier Security Deposit Account (Current Liability) | D8: Other Income Account | E8: After Procurement Head authorization (PC-05)
A9: 4 | B9: Goods received / project completed (IC-verified GRN or Handover) | C9: Relevant Expense or Fixed Asset Account | D9: Accounts Payable | E9: On IC verification (IN-05 / PC-09, PC-10)
A10: 5 | B10: Final supplier payment processed by Finance | C10: Accounts Payable | D10: Bank Account | E10: After the Awaiting Payment notification (FA-01)
A12: NOTES FOR DEVELOPERS
A13: 1. The Procurement module itself posts nothing for purchase orders: financial effects arise only from Finance-confirmed deposits and IC-verified GRNs / Handovers. Deposits are classified as Current Liabilities; forfeitures accrue to Other Income (penalty revenue).
A14: 2. The goods-received entry is identical to the Inventory module entries (IN-13); the Inventory section splits it between expense and stock (asset) items. Confirm the final posting rule once to avoid double posting.

Sheet PC-18 Reports Spec
A1: [Corporation logo] | C1: NORTH COAL STATE OWNED CORPORATION
C2: REQUIRED REPORTS - PROCUREMENT
C3: Every report is generated dynamically in real time with a flexible Custom Date Range filter; standard header/footer as FA-16
A5: # | B5: Report | C5: Frequency | D5: Filter Options | E5: Export
A6: 1 | B6: Bid Comparison and Selection Report | C6: On demand | D6: By contract: competing bids, prices and winning justifications | E6: PDF + Excel
A7: 2 | B7: Procurement Classification Report | C7: On demand | D7: By classification (Goods, Consultancy, Non-Consultancy, Construction, custom) | E7: PDF + Excel
A8: 3 | B8: Project Implementation & Deadline Tracker | C8: Real-time | D8: By implementation %, overdue contracts, extended contracts | E8: PDF + Excel
A9: 4 | B9: Security Deposit Ledger | C9: On demand | D9: Active deposits, refunded, forfeited (transferred to Other Income) | E9: PDF + Excel
A10: 5 | B10: Procurement Activity Report by Method | C10: On demand | D10: Tender / Quotation-Based / Direct Purchase; per period, per department, per Second Unit | E10: PDF + Excel
A11: 6 | B11: Purchase Order / Contract Register | C11: On demand | D11: By status, by supplier, by Second Unit | E11: PDF + Excel
A12: 7 | B12: Pending Purchase Requests Report | C12: Real-time | D12: All requests awaiting Procurement action | E12: PDF + Excel
A13: 8 | B13: Purchase Orders Awaiting Goods Receipt | C13: Real-time | D13: All finalized purchase orders pending IC-verified GRN / Handover | E13: PDF + Excel
A14: 9 | B14: Completed Procurements Report | C14: On demand | D14: All fully completed purchase cycles (per period, per supplier) | E14: PDF + Excel
A15: 10 | B15: Procurement Value by Method Report | C15: Monthly / Annual | D15: Total AFN value per procurement method in the defined period | E15: PDF + Excel
A16: 11 | B16: Supplier Purchase History Report | C16: On demand | D16: Per supplier: all purchase orders, values and delivery records | E16: PDF + Excel
A17: 12 | B17: Internal Control Verification Report | C17: Monthly | D17: By verification outcome (Verified / Rejected) at GRN / Handover stage | E17: PDF + Excel
A18: 13 | B18: Control Log / Audit Trail Report | C18: On demand | D18: By user, date and action type (including extension approvals and unlocks) | E18: PDF + Excel
